{"action":{"identity":{"address":"N\u0000sourcecred\u0000core\u0000IDENTITY\u0000ew3jVpPxQsOzlZCEJCBDWQ\u0000","aliases":[],"id":"ew3jVpPxQsOzlZCEJCBDWQ","name":"Owen-G--G-","subtype":"USER"},"type":"CREATE_IDENTITY"},"ledgerTimestamp":1653354405489,"uuid":"CZYnlbNKSEGoDohecJ7gCg","version":"1"}
{"action":{"alias":{"address":"N\u0000sourcecred\u0000discord\u0000MEMBER\u0000user\u0000307827662196310016\u0000","description":"discord/Owen-G--G-#0187"},"identityId":"ew3jVpPxQsOzlZCEJCBDWQ","type":"ADD_ALIAS"},"ledgerTimestamp":1653354405490,"uuid":"2i6bG5f18N7BAX9gPSpKfQ","version":"1"}
{"action":{"identity":{"address":"N\u0000sourcecred\u0000core\u0000IDENTITY\u0000FAKrNpDqpFwvZNwdKiGhxg\u0000","aliases":[],"id":"FAKrNpDqpFwvZNwdKiGhxg","name":"Michelle42","subtype":"USER"},"type":"CREATE_IDENTITY"},"ledgerTimestamp":1653354405491,"uuid":"ZmuX8e4QABLI963fDAySwg","version":"1"}
{"action":{"alias":{"address":"N\u0000sourcecred\u0000discord\u0000MEMBER\u0000user\u0000932906546982178817\u0000","description":"discord/Michelle42#9528"},"identityId":"FAKrNpDqpFwvZNwdKiGhxg","type":"ADD_ALIAS"},"ledgerTimestamp":1653354405491,"uuid":"wUknE2K9DhqdJkkG2KcEhw","version":"1"}
{"action":{"identity":{"address":"N\u0000sourcecred\u0000core\u0000IDENTITY\u00000cOmbkoHleau1pqnLvbpzw\u0000","aliases":[],"id":"0cOmbkoHleau1pqnLvbpzw","name":"mua-miles","subtype":"USER"},"type":"CREATE_IDENTITY"},"ledgerTimestamp":1653354405491,"uuid":"QzGw1mxMHNx0sM3ULEMXOg","version":"1"}
{"action":{"alias":{"address":"N\u0000sourcecred\u0000discord\u0000MEMBER\u0000user\u0000932919660192620555\u0000","description":"discord/mua-miles#0937"},"identityId":"0cOmbkoHleau1pqnLvbpzw","type":"ADD_ALIAS"},"ledgerTimestamp":1653354405492,"uuid":"GGyQv5eSKt5XDGOGZ67uGg","version":"1"}
{"action":{"identity":{"address":"N\u0000sourcecred\u0000core\u0000IDENTITY\u0000Lk1YS8U6gDJeEdqpArV6Bw\u0000","aliases":[],"id":"Lk1YS8U6gDJeEdqpArV6Bw","name":"mua-sourcecred","subtype":"BOT"},"type":"CREATE_IDENTITY"},"ledgerTimestamp":1653354405492,"uuid":"RwyVxP2gCGdgAMoKq0yAiA","version":"1"}
{"action":{"alias":{"address":"N\u0000sourcecred\u0000discord\u0000MEMBER\u0000bot\u0000933581993118167130\u0000","description":"discord/mua-sourcecred#7651"},"identityId":"Lk1YS8U6gDJeEdqpArV6Bw","type":"ADD_ALIAS"},"ledgerTimestamp":1653354405492,"uuid":"247ww7nIJ58U9rAR1E4fVA","version":"1"}
{"action":{"identity":{"address":"N\u0000sourcecred\u0000core\u0000IDENTITY\u0000CbEaT8qLC1aLh5af42GZyw\u0000","aliases":[],"id":"CbEaT8qLC1aLh5af42GZyw","name":"BigNasty","subtype":"USER"},"type":"CREATE_IDENTITY"},"ledgerTimestamp":1653354405492,"uuid":"SQh5NtXYk2EAU01Rk0kE6g","version":"1"}
{"action":{"alias":{"address":"N\u0000sourcecred\u0000discord\u0000MEMBER\u0000user\u0000248268882920341514\u0000","description":"discord/BigNasty#1633"},"identityId":"CbEaT8qLC1aLh5af42GZyw","type":"ADD_ALIAS"},"ledgerTimestamp":1653354405493,"uuid":"Rp4XCxuN84eNUjS08Qrf2g","version":"1"}
{"action":{"identity":{"address":"N\u0000sourcecred\u0000core\u0000IDENTITY\u0000GT2URcqokFLWw9UmwHzwLA\u0000","aliases":[],"id":"GT2URcqokFLWw9UmwHzwLA","name":"dabBot","subtype":"BOT"},"type":"CREATE_IDENTITY"},"ledgerTimestamp":1653354405493,"uuid":"nmZm028Y0QXGPLM2CxMNGQ","version":"1"}
{"action":{"alias":{"address":"N\u0000sourcecred\u0000discord\u0000MEMBER\u0000bot\u0000270198738570444801\u0000","description":"discord/dabBot#0563"},"identityId":"GT2URcqokFLWw9UmwHzwLA","type":"ADD_ALIAS"},"ledgerTimestamp":1653354405493,"uuid":"ZfAYKBLPz9hk6mlGfE3ckw","version":"1"}
{"action":{"identity":{"address":"N\u0000sourcecred\u0000core\u0000IDENTITY\u0000o3ta7c5vOhmr9ypJRYI7rg\u0000","aliases":[],"id":"o3ta7c5vOhmr9ypJRYI7rg","name":"Zenith","subtype":"USER"},"type":"CREATE_IDENTITY"},"ledgerTimestamp":1653354405493,"uuid":"dd2oyJxn5ENTQPndGdYqnA","version":"1"}
{"action":{"alias":{"address":"N\u0000sourcecred\u0000discord\u0000MEMBER\u0000user\u0000284099355244363777\u0000","description":"discord/Zenith#0305"},"identityId":"o3ta7c5vOhmr9ypJRYI7rg","type":"ADD_ALIAS"},"ledgerTimestamp":1653354405493,"uuid":"LpM2nyCq2NrKQePSN2O5EQ","version":"1"}
{"action":{"identity":{"address":"N\u0000sourcecred\u0000core\u0000IDENTITY\u00008TAnd5xYRhLF3Majoqx8Hw\u0000","aliases":[],"id":"8TAnd5xYRhLF3Majoqx8Hw","name":"wangning","subtype":"USER"},"type":"CREATE_IDENTITY"},"ledgerTimestamp":1653354405493,"uuid":"99gsnQEOqXV8mfyl7gHPYQ","version":"1"}
{"action":{"alias":{"address":"N\u0000sourcecred\u0000discord\u0000MEMBER\u0000user\u0000286231707382710272\u0000","description":"discord/wangning#7822"},"identityId":"8TAnd5xYRhLF3Majoqx8Hw","type":"ADD_ALIAS"},"ledgerTimestamp":1653354405493,"uuid":"FJiVPw3dA7Tqu7e1FzI3Gg","version":"1"}
{"action":{"identity":{"address":"N\u0000sourcecred\u0000core\u0000IDENTITY\u0000yIqdYIYT58PVYVWpRxPyAg\u0000","aliases":[],"id":"yIqdYIYT58PVYVWpRxPyAg","name":"boqunhuai","subtype":"USER"},"type":"CREATE_IDENTITY"},"ledgerTimestamp":1653354405494,"uuid":"0kxRwZQxpetBpKaNzomQcA","version":"1"}
{"action":{"alias":{"address":"N\u0000sourcecred\u0000discord\u0000MEMBER\u0000user\u0000293551775246450718\u0000","description":"discord/boqunhuai#5875"},"identityId":"yIqdYIYT58PVYVWpRxPyAg","type":"ADD_ALIAS"},"ledgerTimestamp":1653354405494,"uuid":"kboprWpMXtr1BGBx4ehx3w","version":"1"}
{"action":{"identity":{"address":"N\u0000sourcecred\u0000core\u0000IDENTITY\u0000JrHpHnoMoMfWCQSxz88AiQ\u0000","aliases":[],"id":"JrHpHnoMoMfWCQSxz88AiQ","name":"Ste","subtype":"USER"},"type":"CREATE_IDENTITY"},"ledgerTimestamp":1653354405494,"uuid":"bkETnEdMZLIglR8eQ8GqIA","version":"1"}
{"action":{"alias":{"address":"N\u0000sourcecred\u0000discord\u0000MEMBER\u0000user\u0000348659265399160832\u0000","description":"discord/Ste#7182"},"identityId":"JrHpHnoMoMfWCQSxz88AiQ","type":"ADD_ALIAS"},"ledgerTimestamp":1653354405495,"uuid":"nWXBzsNIx2vhK9diBrp0wg","version":"1"}
{"action":{"identity":{"address":"N\u0000sourcecred\u0000core\u0000IDENTITY\u0000tWMfruQpwE6ygnDin3BnPA\u0000","aliases":[],"id":"tWMfruQpwE6ygnDin3BnPA","name":"PierreRider","subtype":"USER"},"type":"CREATE_IDENTITY"},"ledgerTimestamp":1653354405495,"uuid":"7KK4eepcZOaKJemF2eLN3w","version":"1"}
{"action":{"alias":{"address":"N\u0000sourcecred\u0000discord\u0000MEMBER\u0000user\u0000382512050389254144\u0000","description":"discord/PierreRider#6186"},"identityId":"tWMfruQpwE6ygnDin3BnPA","type":"ADD_ALIAS"},"ledgerTimestamp":1653354405495,"uuid":"ESdjbpY8dbylvnTPl0O7qA","version":"1"}
{"action":{"identity":{"address":"N\u0000sourcecred\u0000core\u0000IDENTITY\u0000pL5AYGLRDA47ujdKsMpzjw\u0000","aliases":[],"id":"pL5AYGLRDA47ujdKsMpzjw","name":"Holms-pan","subtype":"USER"},"type":"CREATE_IDENTITY"},"ledgerTimestamp":1653354405495,"uuid":"7TqBQ16EvezQxBdJC97ReQ","version":"1"}
{"action":{"alias":{"address":"N\u0000sourcecred\u0000discord\u0000MEMBER\u0000user\u0000388652963289235456\u0000","description":"discord/Holms-pan#3156"},"identityId":"pL5AYGLRDA47ujdKsMpzjw","type":"ADD_ALIAS"},"ledgerTimestamp":1653354405495,"uuid":"ytlh7MLKpQV00vepExaklg","version":"1"}
{"action":{"identity":{"address":"N\u0000sourcecred\u0000core\u0000IDENTITY\u0000U3tjKn0GkzBIWskqJGAtKw\u0000","aliases":[],"id":"U3tjKn0GkzBIWskqJGAtKw","name":"RiverZhou","subtype":"USER"},"type":"CREATE_IDENTITY"},"ledgerTimestamp":1653354405496,"uuid":"gI5uXxW2kyoNMH43Iv8ykg","version":"1"}
{"action":{"alias":{"address":"N\u0000sourcecred\u0000discord\u0000MEMBER\u0000user\u0000406452285284024330\u0000","description":"discord/RiverZhou#9269"},"identityId":"U3tjKn0GkzBIWskqJGAtKw","type":"ADD_ALIAS"},"ledgerTimestamp":1653354405496,"uuid":"L4AL6ED5Wslyq2p7ePFrow","version":"1"}
{"action":{"identity":{"address":"N\u0000sourcecred\u0000core\u0000IDENTITY\u0000iOLedepVeKozMVrmVKxFLw\u0000","aliases":[],"id":"iOLedepVeKozMVrmVKxFLw","name":"Anvason","subtype":"USER"},"type":"CREATE_IDENTITY"},"ledgerTimestamp":1653354405496,"uuid":"sVjB9Hvrq5lA9VUVhWjqqA","version":"1"}
{"action":{"alias":{"address":"N\u0000sourcecred\u0000discord\u0000MEMBER\u0000user\u0000413226394533756928\u0000","description":"discord/Anvason#1087"},"identityId":"iOLedepVeKozMVrmVKxFLw","type":"ADD_ALIAS"},"ledgerTimestamp":1653354405496,"uuid":"1aNmyHqrQJCLOYHkQ2a7mQ","version":"1"}
{"action":{"identity":{"address":"N\u0000sourcecred\u0000core\u0000IDENTITY\u0000pTBCMDs0X2SNjc9Earn1VA\u0000","aliases":[],"id":"pTBCMDs0X2SNjc9Earn1VA","name":"echo","subtype":"USER"},"type":"CREATE_IDENTITY"},"ledgerTimestamp":1653354405496,"uuid":"eIvDwoj29VNGJ22XwOI3cg","version":"1"}
{"action":{"alias":{"address":"N\u0000sourcecred\u0000discord\u0000MEMBER\u0000user\u0000416244528815669248\u0000","description":"discord/echo#0970"},"identityId":"pTBCMDs0X2SNjc9Earn1VA","type":"ADD_ALIAS"},"ledgerTimestamp":1653354405496,"uuid":"r6bvxa8zNDb9BB4XtBy1Vg","version":"1"}
{"action":{"identity":{"address":"N\u0000sourcecred\u0000core\u0000IDENTITY\u00007Js5bWwYbhOFRW5BBYe8Mg\u0000","aliases":[],"id":"7Js5bWwYbhOFRW5BBYe8Mg","name":"EasyPoll","subtype":"BOT"},"type":"CREATE_IDENTITY"},"ledgerTimestamp":1653354405497,"uuid":"z7wMDei7QdFXvoDSdIKKGw","version":"1"}
{"action":{"alias":{"address":"N\u0000sourcecred\u0000discord\u0000MEMBER\u0000bot\u0000437618149505105920\u0000","description":"discord/EasyPoll#3712"},"identityId":"7Js5bWwYbhOFRW5BBYe8Mg","type":"ADD_ALIAS"},"ledgerTimestamp":1653354405497,"uuid":"4E1N78qeB6KDRQMOaRc2kA","version":"1"}
{"action":{"identity":{"address":"N\u0000sourcecred\u0000core\u0000IDENTITY\u0000Xn1LVHJ2vwbYeFmW5J8vPw\u0000","aliases":[],"id":"Xn1LVHJ2vwbYeFmW5J8vPw","name":"rosy","subtype":"USER"},"type":"CREATE_IDENTITY"},"ledgerTimestamp":1653354405497,"uuid":"D9vnQG1qznxW657oXRDkAQ","version":"1"}
{"action":{"alias":{"address":"N\u0000sourcecred\u0000discord\u0000MEMBER\u0000user\u0000445181248558858261\u0000","description":"discord/rosy#6688"},"identityId":"Xn1LVHJ2vwbYeFmW5J8vPw","type":"ADD_ALIAS"},"ledgerTimestamp":1653354405497,"uuid":"N5Hrz5ghrPy8HPV5pCL3Ag","version":"1"}
{"action":{"identity":{"address":"N\u0000sourcecred\u0000core\u0000IDENTITY\u00001Qi707hnLqRmsOJPjkzxqQ\u0000","aliases":[],"id":"1Qi707hnLqRmsOJPjkzxqQ","name":"toothbrushkon","subtype":"USER"},"type":"CREATE_IDENTITY"},"ledgerTimestamp":1653354405498,"uuid":"jJJ1F9ehejYlxiM031ylzw","version":"1"}
{"action":{"alias":{"address":"N\u0000sourcecred\u0000discord\u0000MEMBER\u0000user\u0000446117131776688143\u0000","description":"discord/toothbrushkon#9424"},"identityId":"1Qi707hnLqRmsOJPjkzxqQ","type":"ADD_ALIAS"},"ledgerTimestamp":1653354405498,"uuid":"zjPNG6FrCvoHXvFdiV2lZQ","version":"1"}
{"action":{"identity":{"address":"N\u0000sourcecred\u0000core\u0000IDENTITY\u0000MLq029KSMeYpDSpTJ6j0KQ\u0000","aliases":[],"id":"MLq029KSMeYpDSpTJ6j0KQ","name":"stickydog","subtype":"USER"},"type":"CREATE_IDENTITY"},"ledgerTimestamp":1653354405498,"uuid":"EOEiw5HQWo1Q8r8I0VqlLw","version":"1"}
{"action":{"alias":{"address":"N\u0000sourcecred\u0000discord\u0000MEMBER\u0000user\u0000451956288570785792\u0000","description":"discord/stickydog#5376"},"identityId":"MLq029KSMeYpDSpTJ6j0KQ","type":"ADD_ALIAS"},"ledgerTimestamp":1653354405498,"uuid":"OpdK3QabNSJA1t2HDhK1jA","version":"1"}
{"action":{"identity":{"address":"N\u0000sourcecred\u0000core\u0000IDENTITY\u0000oePNCRMsXheVXy9v150NgQ\u0000","aliases":[],"id":"oePNCRMsXheVXy9v150NgQ","name":"---258","subtype":"USER"},"type":"CREATE_IDENTITY"},"ledgerTimestamp":1653354405499,"uuid":"DWVnU7xUqG8vekJV0HX3kg","version":"1"}
{"action":{"alias":{"address":"N\u0000sourcecred\u0000discord\u0000MEMBER\u0000user\u0000483543801458196480\u0000","description":"discord/---258#8422"},"identityId":"oePNCRMsXheVXy9v150NgQ","type":"ADD_ALIAS"},"ledgerTimestamp":1653354405499,"uuid":"HgNF9r1w2LjB9WLQzmEIzg","version":"1"}
{"action":{"identity":{"address":"N\u0000sourcecred\u0000core\u0000IDENTITY\u0000NBZKAXDvPlEF3MDwxDkzWQ\u0000","aliases":[],"id":"NBZKAXDvPlEF3MDwxDkzWQ","name":"Lofi-Radio","subtype":"BOT"},"type":"CREATE_IDENTITY"},"ledgerTimestamp":1653354405499,"uuid":"Eag7Ph6KV4ulWH3lUv3hbQ","version":"1"}
{"action":{"alias":{"address":"N\u0000sourcecred\u0000discord\u0000MEMBER\u0000bot\u0000497894401264058368\u0000","description":"discord/Lofi-Radio#8044"},"identityId":"NBZKAXDvPlEF3MDwxDkzWQ","type":"ADD_ALIAS"},"ledgerTimestamp":1653354405503,"uuid":"86weaQ0iLxG90g17oRxhKA","version":"1"}
{"action":{"identity":{"address":"N\u0000sourcecred\u0000core\u0000IDENTITY\u0000MLxLNen1nwO0zW7Ov4Jk8g\u0000","aliases":[],"id":"MLxLNen1nwO0zW7Ov4Jk8g","name":"Tickets","subtype":"BOT"},"type":"CREATE_IDENTITY"},"ledgerTimestamp":1653354405503,"uuid":"65dQdJcPxZEOdtqr70A3dw","version":"1"}
{"action":{"alias":{"address":"N\u0000sourcecred\u0000discord\u0000MEMBER\u0000bot\u0000508391840525975553\u0000","description":"discord/Tickets#6981"},"identityId":"MLxLNen1nwO0zW7Ov4Jk8g","type":"ADD_ALIAS"},"ledgerTimestamp":1653354405503,"uuid":"ezcyeyX0f1V52J0hwqSR5g","version":"1"}
{"action":{"identity":{"address":"N\u0000sourcecred\u0000core\u0000IDENTITY\u00006MKYnwnC0UNI9DmbWv5oRA\u0000","aliases":[],"id":"6MKYnwnC0UNI9DmbWv5oRA","name":"mr-sheepz","subtype":"USER"},"type":"CREATE_IDENTITY"},"ledgerTimestamp":1653354405503,"uuid":"zSLCx0axdSZDyjGqc1qDmw","version":"1"}
{"action":{"alias":{"address":"N\u0000sourcecred\u0000discord\u0000MEMBER\u0000user\u0000508770359751737355\u0000","description":"discord/mr-sheepz#6828"},"identityId":"6MKYnwnC0UNI9DmbWv5oRA","type":"ADD_ALIAS"},"ledgerTimestamp":1653354405503,"uuid":"LGxUD2OkVuGF7fVagKqZCw","version":"1"}
{"action":{"identity":{"address":"N\u0000sourcecred\u0000core\u0000IDENTITY\u0000im3jYx6yNeD5t1kNLW4XgQ\u0000","aliases":[],"id":"im3jYx6yNeD5t1kNLW4XgQ","name":"imdabao","subtype":"USER"},"type":"CREATE_IDENTITY"},"ledgerTimestamp":1653354405503,"uuid":"SNeM3O3DrrYJiGCgr1Jsrg","version":"1"}
{"action":{"alias":{"address":"N\u0000sourcecred\u0000discord\u0000MEMBER\u0000user\u0000545183584038944810\u0000","description":"discord/imdabao#0329"},"identityId":"im3jYx6yNeD5t1kNLW4XgQ","type":"ADD_ALIAS"},"ledgerTimestamp":1653354405504,"uuid":"pj47K4kbLWzJdBwFapHEjw","version":"1"}
{"action":{"identity":{"address":"N\u0000sourcecred\u0000core\u0000IDENTITY\u0000sJouL9mGc2rhenOkf5l3EQ\u0000","aliases":[],"id":"sJouL9mGc2rhenOkf5l3EQ","name":"gisou","subtype":"USER"},"type":"CREATE_IDENTITY"},"ledgerTimestamp":1653354405504,"uuid":"3ZfG7UGFvHOjXyLuocZSXQ","version":"1"}
{"action":{"alias":{"address":"N\u0000sourcecred\u0000discord\u0000MEMBER\u0000user\u0000546831540152303617\u0000","description":"discord/gisou#1603"},"identityId":"sJouL9mGc2rhenOkf5l3EQ","type":"ADD_ALIAS"},"ledgerTimestamp":1653354405504,"uuid":"inCgQgxtJJ8EaHEJGiLzbw","version":"1"}
{"action":{"identity":{"address":"N\u0000sourcecred\u0000core\u0000IDENTITY\u0000UVIKAM0Tjkgr7jpMb0gpSw\u0000","aliases":[],"id":"UVIKAM0Tjkgr7jpMb0gpSw","name":"CaptainTang","subtype":"USER"},"type":"CREATE_IDENTITY"},"ledgerTimestamp":1653354405504,"uuid":"nmgy5NrVwABWmX9sBQE0TA","version":"1"}
{"action":{"alias":{"address":"N\u0000sourcecred\u0000discord\u0000MEMBER\u0000user\u0000556958324436893696\u0000","description":"discord/CaptainTang#1828"},"identityId":"UVIKAM0Tjkgr7jpMb0gpSw","type":"ADD_ALIAS"},"ledgerTimestamp":1653354405504,"uuid":"tYPdty3DylzsDs3NQbuavQ","version":"1"}
{"action":{"identity":{"address":"N\u0000sourcecred\u0000core\u0000IDENTITY\u0000wou9WupfyPClJUXRf5562A\u0000","aliases":[],"id":"wou9WupfyPClJUXRf5562A","name":"Ticket-Tool","subtype":"BOT"},"type":"CREATE_IDENTITY"},"ledgerTimestamp":1653354405504,"uuid":"HxgmV1lIyFvYnUOeKGQAtw","version":"1"}
{"action":{"alias":{"address":"N\u0000sourcecred\u0000discord\u0000MEMBER\u0000bot\u0000557628352828014614\u0000","description":"discord/Ticket-Tool#4843"},"identityId":"wou9WupfyPClJUXRf5562A","type":"ADD_ALIAS"},"ledgerTimestamp":1653354405505,"uuid":"La4LPhozBqomDWpwRnCrpg","version":"1"}
{"action":{"identity":{"address":"N\u0000sourcecred\u0000core\u0000IDENTITY\u0000zTjrygziB5LGBOcGkMycoA\u0000","aliases":[],"id":"zTjrygziB5LGBOcGkMycoA","name":"StrayTrue","subtype":"USER"},"type":"CREATE_IDENTITY"},"ledgerTimestamp":1653354405505,"uuid":"4ua8cmFnLaDIz8TGnqwadQ","version":"1"}
{"action":{"alias":{"address":"N\u0000sourcecred\u0000discord\u0000MEMBER\u0000user\u0000570891552457490432\u0000","description":"discord/StrayTrue#4389"},"identityId":"zTjrygziB5LGBOcGkMycoA","type":"ADD_ALIAS"},"ledgerTimestamp":1653354405505,"uuid":"vhd1WagO82AfezvfGjadOQ","version":"1"}
{"action":{"identity":{"address":"N\u0000sourcecred\u0000core\u0000IDENTITY\u0000r1hrrSXumOMERnFKDQ6oKw\u0000","aliases":[],"id":"r1hrrSXumOMERnFKDQ6oKw","name":"KJ---lowpolymodelsworld-com","subtype":"USER"},"type":"CREATE_IDENTITY"},"ledgerTimestamp":1653354405505,"uuid":"Oh4YngdqQiO6Cap3Jcj7qQ","version":"1"}
{"action":{"alias":{"address":"N\u0000sourcecred\u0000discord\u0000MEMBER\u0000user\u0000584069387439570964\u0000","description":"discord/KJ---lowpolymodelsworld-com#4964"},"identityId":"r1hrrSXumOMERnFKDQ6oKw","type":"ADD_ALIAS"},"ledgerTimestamp":1653354405505,"uuid":"qyD860OW9tj82LezsmTPSQ","version":"1"}
{"action":{"identity":{"address":"N\u0000sourcecred\u0000core\u0000IDENTITY\u0000fgIRP6GWh9ZLfkMndqQfkA\u0000","aliases":[],"id":"fgIRP6GWh9ZLfkMndqQfkA","name":"GreatCarls","subtype":"USER"},"type":"CREATE_IDENTITY"},"ledgerTimestamp":1653354405505,"uuid":"NwApwXTok9GuDbBjFDrKww","version":"1"}
{"action":{"alias":{"address":"N\u0000sourcecred\u0000discord\u0000MEMBER\u0000user\u0000627665531469692958\u0000","description":"discord/GreatCarls#0001"},"identityId":"fgIRP6GWh9ZLfkMndqQfkA","type":"ADD_ALIAS"},"ledgerTimestamp":1653354405506,"uuid":"0yvIWiWeu7fbrzkJmLK94w","version":"1"}
{"action":{"identity":{"address":"N\u0000sourcecred\u0000core\u0000IDENTITY\u00000ePSnaaa3eykLos3VKiJgw\u0000","aliases":[],"id":"0ePSnaaa3eykLos3VKiJgw","name":"SuperTomato","subtype":"USER"},"type":"CREATE_IDENTITY"},"ledgerTimestamp":1653354405506,"uuid":"3u26tL6gvF0I212u6Z9BpQ","version":"1"}
{"action":{"alias":{"address":"N\u0000sourcecred\u0000discord\u0000MEMBER\u0000user\u0000630752333373898762\u0000","description":"discord/SuperTomato#9824"},"identityId":"0ePSnaaa3eykLos3VKiJgw","type":"ADD_ALIAS"},"ledgerTimestamp":1653354405506,"uuid":"NkxmkKpgGawjRWGt24GBRg","version":"1"}
{"action":{"identity":{"address":"N\u0000sourcecred\u0000core\u0000IDENTITY\u00009ae4SeGKqdlT0cXxngGiOg\u0000","aliases":[],"id":"9ae4SeGKqdlT0cXxngGiOg","name":"--CloudZjx","subtype":"USER"},"type":"CREATE_IDENTITY"},"ledgerTimestamp":1653354405506,"uuid":"0qJ1TbtKBRJZcYT7B0CYxA","version":"1"}
{"action":{"alias":{"address":"N\u0000sourcecred\u0000discord\u0000MEMBER\u0000user\u0000636422227692093450\u0000","description":"discord/--CloudZjx#9865"},"identityId":"9ae4SeGKqdlT0cXxngGiOg","type":"ADD_ALIAS"},"ledgerTimestamp":1653354405506,"uuid":"vcPRV1myz32JmwPnBdK2Cg","version":"1"}
{"action":{"identity":{"address":"N\u0000sourcecred\u0000core\u0000IDENTITY\u0000xgtOENRrobahR3bmQUPyPA\u0000","aliases":[],"id":"xgtOENRrobahR3bmQUPyPA","name":"JustFEMI","subtype":"USER"},"type":"CREATE_IDENTITY"},"ledgerTimestamp":1653354405506,"uuid":"ogMi04DtbeQ14N5B119v7Q","version":"1"}
{"action":{"alias":{"address":"N\u0000sourcecred\u0000discord\u0000MEMBER\u0000user\u0000650011519131713547\u0000","description":"discord/JustFEMI#8853"},"identityId":"xgtOENRrobahR3bmQUPyPA","type":"ADD_ALIAS"},"ledgerTimestamp":1653354405506,"uuid":"KDje3Dz1QGQMXtzcGXxeCA","version":"1"}
{"action":{"identity":{"address":"N\u0000sourcecred\u0000core\u0000IDENTITY\u0000iGE2Bbc06dbY9dHN8R1lzQ\u0000","aliases":[],"id":"iGE2Bbc06dbY9dHN8R1lzQ","name":"Melis--zkaya","subtype":"USER"},"type":"CREATE_IDENTITY"},"ledgerTimestamp":1653354405506,"uuid":"BiGcomO7K4V542RdLjbt9Q","version":"1"}
{"action":{"alias":{"address":"N\u0000sourcecred\u0000discord\u0000MEMBER\u0000user\u0000701136232297791568\u0000","description":"discord/Melis--zkaya#7324"},"identityId":"iGE2Bbc06dbY9dHN8R1lzQ","type":"ADD_ALIAS"},"ledgerTimestamp":1653354405507,"uuid":"gwV5S3MCmDli6M9rBIdjhg","version":"1"}
{"action":{"identity":{"address":"N\u0000sourcecred\u0000core\u0000IDENTITY\u0000QXvbRgimfZEjo28OiR35pg\u0000","aliases":[],"id":"QXvbRgimfZEjo28OiR35pg","name":"Collab-Land","subtype":"BOT"},"type":"CREATE_IDENTITY"},"ledgerTimestamp":1653354405507,"uuid":"tkYzWMbqtAv4PpXZ3XbLVA","version":"1"}
{"action":{"alias":{"address":"N\u0000sourcecred\u0000discord\u0000MEMBER\u0000bot\u0000704521096837464076\u0000","description":"discord/Collab-Land#6372"},"identityId":"QXvbRgimfZEjo28OiR35pg","type":"ADD_ALIAS"},"ledgerTimestamp":1653354405507,"uuid":"Dbytkm1QwWHYCny6x1LD2Q","version":"1"}
{"action":{"identity":{"address":"N\u0000sourcecred\u0000core\u0000IDENTITY\u00001mg2pT5Gqmm6DW7OzW8fbQ\u0000","aliases":[],"id":"1mg2pT5Gqmm6DW7OzW8fbQ","name":"Yi","subtype":"USER"},"type":"CREATE_IDENTITY"},"ledgerTimestamp":1653354405507,"uuid":"bh26Qpf7xO0yBg1XoN10Hw","version":"1"}
{"action":{"alias":{"address":"N\u0000sourcecred\u0000discord\u0000MEMBER\u0000user\u0000716060594268143677\u0000","description":"discord/Yi#2779"},"identityId":"1mg2pT5Gqmm6DW7OzW8fbQ","type":"ADD_ALIAS"},"ledgerTimestamp":1653354405507,"uuid":"iXqVoyomTEqjiXGvah12uw","version":"1"}
{"action":{"identity":{"address":"N\u0000sourcecred\u0000core\u0000IDENTITY\u0000jQC1xKZEuVWLFe8gn6E7Mw\u0000","aliases":[],"id":"jQC1xKZEuVWLFe8gn6E7Mw","name":"Invite-Tracker","subtype":"BOT"},"type":"CREATE_IDENTITY"},"ledgerTimestamp":1653354405508,"uuid":"kiXtBwrf78LVsmsZqnxGuQ","version":"1"}
{"action":{"alias":{"address":"N\u0000sourcecred\u0000discord\u0000MEMBER\u0000bot\u0000720351927581278219\u0000","description":"discord/Invite-Tracker#0478"},"identityId":"jQC1xKZEuVWLFe8gn6E7Mw","type":"ADD_ALIAS"},"ledgerTimestamp":1653354405508,"uuid":"tbv8XKzs49LvnAxYgcPQAw","version":"1"}
{"action":{"identity":{"address":"N\u0000sourcecred\u0000core\u0000IDENTITY\u0000NnRSKD5X2BG2KvZ7OAe7gg\u0000","aliases":[],"id":"NnRSKD5X2BG2KvZ7OAe7gg","name":"discord-731137393733795973","subtype":"USER"},"type":"CREATE_IDENTITY"},"ledgerTimestamp":1653354405508,"uuid":"l2Svzbhkg0cVQPB1JmKO3w","version":"1"}
{"action":{"alias":{"address":"N\u0000sourcecred\u0000discord\u0000MEMBER\u0000user\u0000731137393733795973\u0000","description":"discord/discord-731137393733795973#4210"},"identityId":"NnRSKD5X2BG2KvZ7OAe7gg","type":"ADD_ALIAS"},"ledgerTimestamp":1653354405508,"uuid":"87yLec10v2BQkGDEaRJ3EQ","version":"1"}
{"action":{"identity":{"address":"N\u0000sourcecred\u0000core\u0000IDENTITY\u0000y0t0IlV3U4dYpZoqzAnKZw\u0000","aliases":[],"id":"y0t0IlV3U4dYpZoqzAnKZw","name":"Vaporfish","subtype":"USER"},"type":"CREATE_IDENTITY"},"ledgerTimestamp":1653354405508,"uuid":"IviLQrZrN9WbOSRAXQqs2Q","version":"1"}
{"action":{"alias":{"address":"N\u0000sourcecred\u0000discord\u0000MEMBER\u0000user\u0000732347338970103880\u0000","description":"discord/Vaporfish#4083"},"identityId":"y0t0IlV3U4dYpZoqzAnKZw","type":"ADD_ALIAS"},"ledgerTimestamp":1653354405508,"uuid":"M3C0XVjD4d7XcyPa0Ju0Gg","version":"1"}
{"action":{"identity":{"address":"N\u0000sourcecred\u0000core\u0000IDENTITY\u0000VrYm3XbPv1e2LHJW44BVBQ\u0000","aliases":[],"id":"VrYm3XbPv1e2LHJW44BVBQ","name":"Owen2021","subtype":"USER"},"type":"CREATE_IDENTITY"},"ledgerTimestamp":1653354405509,"uuid":"5Q7ZTryAdrelZcLWoMM1zQ","version":"1"}
{"action":{"alias":{"address":"N\u0000sourcecred\u0000discord\u0000MEMBER\u0000user\u0000733266320077881365\u0000","description":"discord/Owen2021#1568"},"identityId":"VrYm3XbPv1e2LHJW44BVBQ","type":"ADD_ALIAS"},"ledgerTimestamp":1653354405509,"uuid":"VIjNYxQPlBiYbMsWC6bPcw","version":"1"}
{"action":{"identity":{"address":"N\u0000sourcecred\u0000core\u0000IDENTITY\u0000z3vjcdjn2GyIZtOn8os4IA\u0000","aliases":[],"id":"z3vjcdjn2GyIZtOn8os4IA","name":"MrDhingia","subtype":"USER"},"type":"CREATE_IDENTITY"},"ledgerTimestamp":1653354405509,"uuid":"SkkeNup5eI6R3Rh9qkDTdQ","version":"1"}
{"action":{"alias":{"address":"N\u0000sourcecred\u0000discord\u0000MEMBER\u0000user\u0000737229138972377158\u0000","description":"discord/MrDhingia#6908"},"identityId":"z3vjcdjn2GyIZtOn8os4IA","type":"ADD_ALIAS"},"ledgerTimestamp":1653354405509,"uuid":"3jwY2uMLQ8fZ7xUw99v0sg","version":"1"}
{"action":{"identity":{"address":"N\u0000sourcecred\u0000core\u0000IDENTITY\u0000XkzXjvUwbnzYZSOlfAmyLg\u0000","aliases":[],"id":"XkzXjvUwbnzYZSOlfAmyLg","name":"MANWANG0723","subtype":"USER"},"type":"CREATE_IDENTITY"},"ledgerTimestamp":1653354405509,"uuid":"Evj7yim9KQiLwgZF0HMN4g","version":"1"}
{"action":{"alias":{"address":"N\u0000sourcecred\u0000discord\u0000MEMBER\u0000user\u0000743670950364446823\u0000","description":"discord/MANWANG0723#2285"},"identityId":"XkzXjvUwbnzYZSOlfAmyLg","type":"ADD_ALIAS"},"ledgerTimestamp":1653354405509,"uuid":"XRwVA3VsrgMI05Bl4Mz7iA","version":"1"}
{"action":{"identity":{"address":"N\u0000sourcecred\u0000core\u0000IDENTITY\u0000Dl38wR2jVc4Rw9vHErtKCA\u0000","aliases":[],"id":"Dl38wR2jVc4Rw9vHErtKCA","name":"smaug---MUA","subtype":"USER"},"type":"CREATE_IDENTITY"},"ledgerTimestamp":1653354405510,"uuid":"uj5aRWf9ahq8BxnoFYOHoA","version":"1"}
{"action":{"alias":{"address":"N\u0000sourcecred\u0000discord\u0000MEMBER\u0000user\u0000743733413223071774\u0000","description":"discord/smaug---MUA#9494"},"identityId":"Dl38wR2jVc4Rw9vHErtKCA","type":"ADD_ALIAS"},"ledgerTimestamp":1653354405510,"uuid":"uVDTl0CBQSZ5ZaW89ptltw","version":"1"}
{"action":{"identity":{"address":"N\u0000sourcecred\u0000core\u0000IDENTITY\u000000yW1fYyxUxaDLFm1sDCqw\u0000","aliases":[],"id":"00yW1fYyxUxaDLFm1sDCqw","name":"Tomasu","subtype":"USER"},"type":"CREATE_IDENTITY"},"ledgerTimestamp":1653354405510,"uuid":"SdjkAWO1X8VrD5nzd0ERSA","version":"1"}
{"action":{"alias":{"address":"N\u0000sourcecred\u0000discord\u0000MEMBER\u0000user\u0000744491938459287583\u0000","description":"discord/Tomasu#2144"},"identityId":"00yW1fYyxUxaDLFm1sDCqw","type":"ADD_ALIAS"},"ledgerTimestamp":1653354405510,"uuid":"UNHW5RgDevp8QvyDjS9g4w","version":"1"}
{"action":{"identity":{"address":"N\u0000sourcecred\u0000core\u0000IDENTITY\u0000QrplcBtXEyQ3OPLu4JTQag\u0000","aliases":[],"id":"QrplcBtXEyQ3OPLu4JTQag","name":"Yuan","subtype":"USER"},"type":"CREATE_IDENTITY"},"ledgerTimestamp":1653354405510,"uuid":"hP9yWnBbk74gEqofyUKCkA","version":"1"}
{"action":{"alias":{"address":"N\u0000sourcecred\u0000discord\u0000MEMBER\u0000user\u0000746300239773696073\u0000","description":"discord/Yuan#6482"},"identityId":"QrplcBtXEyQ3OPLu4JTQag","type":"ADD_ALIAS"},"ledgerTimestamp":1653354405510,"uuid":"xnXrmGYiXTlN6EauaM75xg","version":"1"}
{"action":{"identity":{"address":"N\u0000sourcecred\u0000core\u0000IDENTITY\u0000nK07w0ELYVkVvbFoG1vYCw\u0000","aliases":[],"id":"nK07w0ELYVkVvbFoG1vYCw","name":"corey","subtype":"USER"},"type":"CREATE_IDENTITY"},"ledgerTimestamp":1653354405511,"uuid":"8G3kBfVj6qbEjAujvdkoxw","version":"1"}
{"action":{"alias":{"address":"N\u0000sourcecred\u0000discord\u0000MEMBER\u0000user\u0000770599426740846592\u0000","description":"discord/corey#2063"},"identityId":"nK07w0ELYVkVvbFoG1vYCw","type":"ADD_ALIAS"},"ledgerTimestamp":1653354405511,"uuid":"ezkDaGuP5BQbvxfeUPaZsw","version":"1"}
{"action":{"identity":{"address":"N\u0000sourcecred\u0000core\u0000IDENTITY\u00002VvrWvbJ84nI3LvgKpN3Pg\u0000","aliases":[],"id":"2VvrWvbJ84nI3LvgKpN3Pg","name":"Zuiiun","subtype":"USER"},"type":"CREATE_IDENTITY"},"ledgerTimestamp":1653354405511,"uuid":"kag0RmAjwJUrYxAnTngnQQ","version":"1"}
{"action":{"alias":{"address":"N\u0000sourcecred\u0000discord\u0000MEMBER\u0000user\u0000773233506972205106\u0000","description":"discord/Zuiiun#9137"},"identityId":"2VvrWvbJ84nI3LvgKpN3Pg","type":"ADD_ALIAS"},"ledgerTimestamp":1653354405511,"uuid":"CZ3G2JnDgU1E5qNGMQKfDg","version":"1"}
{"action":{"identity":{"address":"N\u0000sourcecred\u0000core\u0000IDENTITY\u0000tZzkJi6oR6Rpevf1cd3OZw\u0000","aliases":[],"id":"tZzkJi6oR6Rpevf1cd3OZw","name":"chakshaw","subtype":"USER"},"type":"CREATE_IDENTITY"},"ledgerTimestamp":1653354405511,"uuid":"8ngsz4JvYTN0DQ2bYwFX2Q","version":"1"}
{"action":{"alias":{"address":"N\u0000sourcecred\u0000discord\u0000MEMBER\u0000user\u0000800338219837161473\u0000","description":"discord/chakshaw#6750"},"identityId":"tZzkJi6oR6Rpevf1cd3OZw","type":"ADD_ALIAS"},"ledgerTimestamp":1653354405511,"uuid":"ea9qzrwZqI7bPSZ2Myh5ow","version":"1"}
{"action":{"identity":{"address":"N\u0000sourcecred\u0000core\u0000IDENTITY\u0000MBBvCdkUa56WtkBvHpQ8rg\u0000","aliases":[],"id":"MBBvCdkUa56WtkBvHpQ8rg","name":"Adoo--D","subtype":"USER"},"type":"CREATE_IDENTITY"},"ledgerTimestamp":1653354405511,"uuid":"WUBQOVNDw0AGKQtvXf7mSg","version":"1"}
{"action":{"alias":{"address":"N\u0000sourcecred\u0000discord\u0000MEMBER\u0000user\u0000802119263883100170\u0000","description":"discord/Adoo--D#9951"},"identityId":"MBBvCdkUa56WtkBvHpQ8rg","type":"ADD_ALIAS"},"ledgerTimestamp":1653354405511,"uuid":"uLkHqJQs16xF6DKVGJt0Vw","version":"1"}
{"action":{"identity":{"address":"N\u0000sourcecred\u0000core\u0000IDENTITY\u0000iOtEkxfbXAxBfqoM5rUQXg\u0000","aliases":[],"id":"iOtEkxfbXAxBfqoM5rUQXg","name":"kaf","subtype":"USER"},"type":"CREATE_IDENTITY"},"ledgerTimestamp":1653354405512,"uuid":"6jZfkOdbbyiYFXMSZy3dRw","version":"1"}
{"action":{"alias":{"address":"N\u0000sourcecred\u0000discord\u0000MEMBER\u0000user\u0000806501590369828885\u0000","description":"discord/kaf#6633"},"identityId":"iOtEkxfbXAxBfqoM5rUQXg","type":"ADD_ALIAS"},"ledgerTimestamp":1653354405512,"uuid":"e2BDiQ8oaCAJu3g6vmBorA","version":"1"}
{"action":{"identity":{"address":"N\u0000sourcecred\u0000core\u0000IDENTITY\u0000gzytkmVb8D8penV9LBIvTQ\u0000","aliases":[],"id":"gzytkmVb8D8penV9LBIvTQ","name":"miles","subtype":"USER"},"type":"CREATE_IDENTITY"},"ledgerTimestamp":1653354405512,"uuid":"Hg0JcmfPg1rku99CnqPYig","version":"1"}
{"action":{"alias":{"address":"N\u0000sourcecred\u0000discord\u0000MEMBER\u0000user\u0000808639304402337834\u0000","description":"discord/miles#8593"},"identityId":"gzytkmVb8D8penV9LBIvTQ","type":"ADD_ALIAS"},"ledgerTimestamp":1653354405512,"uuid":"h2udDqjzx6197HJwvNp4uQ","version":"1"}
{"action":{"identity":{"address":"N\u0000sourcecred\u0000core\u0000IDENTITY\u00001xQGvPdG4QU9zclxx07czg\u0000","aliases":[],"id":"1xQGvPdG4QU9zclxx07czg","name":"UltraLeo","subtype":"USER"},"type":"CREATE_IDENTITY"},"ledgerTimestamp":1653354405512,"uuid":"X1SbaCNNzONuDybRb8GwLg","version":"1"}
{"action":{"alias":{"address":"N\u0000sourcecred\u0000discord\u0000MEMBER\u0000user\u0000812919116578816050\u0000","description":"discord/UltraLeo#8556"},"identityId":"1xQGvPdG4QU9zclxx07czg","type":"ADD_ALIAS"},"ledgerTimestamp":1653354405512,"uuid":"wiKfDZYAO1JrAqzoR0V4Tg","version":"1"}
{"action":{"identity":{"address":"N\u0000sourcecred\u0000core\u0000IDENTITY\u0000UlTdmkSQDiLLMNOf10Ynpg\u0000","aliases":[],"id":"UlTdmkSQDiLLMNOf10Ynpg","name":"Jonas-Zhao","subtype":"USER"},"type":"CREATE_IDENTITY"},"ledgerTimestamp":1653354405512,"uuid":"SXD34mEDbASG5bfYowsLOg","version":"1"}
{"action":{"alias":{"address":"N\u0000sourcecred\u0000discord\u0000MEMBER\u0000user\u0000823004558132510750\u0000","description":"discord/Jonas-Zhao#7359"},"identityId":"UlTdmkSQDiLLMNOf10Ynpg","type":"ADD_ALIAS"},"ledgerTimestamp":1653354405513,"uuid":"iL9oRBGdbfJyc2aPK9EQqA","version":"1"}
{"action":{"identity":{"address":"N\u0000sourcecred\u0000core\u0000IDENTITY\u0000Lr0jBQ3oYEvGwR0YYtm3Kw\u0000","aliases":[],"id":"Lr0jBQ3oYEvGwR0YYtm3Kw","name":"MaeGanYork","subtype":"USER"},"type":"CREATE_IDENTITY"},"ledgerTimestamp":1653354405513,"uuid":"iyzwXX87DAu15XzVb3EznA","version":"1"}
{"action":{"alias":{"address":"N\u0000sourcecred\u0000discord\u0000MEMBER\u0000user\u0000827466301949214721\u0000","description":"discord/MaeGanYork#9864"},"identityId":"Lr0jBQ3oYEvGwR0YYtm3Kw","type":"ADD_ALIAS"},"ledgerTimestamp":1653354405513,"uuid":"T4n3Rdppj2hZ2AF0HxIyDw","version":"1"}
{"action":{"identity":{"address":"N\u0000sourcecred\u0000core\u0000IDENTITY\u0000PPG76JdLL9vCe712Kb2uMg\u0000","aliases":[],"id":"PPG76JdLL9vCe712Kb2uMg","name":"bocai","subtype":"USER"},"type":"CREATE_IDENTITY"},"ledgerTimestamp":1653354405513,"uuid":"aAJ569xecgweNwzeADvdlA","version":"1"}
{"action":{"alias":{"address":"N\u0000sourcecred\u0000discord\u0000MEMBER\u0000user\u0000841967178453745676\u0000","description":"discord/bocai#1635"},"identityId":"PPG76JdLL9vCe712Kb2uMg","type":"ADD_ALIAS"},"ledgerTimestamp":1653354405513,"uuid":"e0svKmh22HvGnzoJMhQwww","version":"1"}
{"action":{"identity":{"address":"N\u0000sourcecred\u0000core\u0000IDENTITY\u0000ZLCzXpHn947bPh5owkWUwQ\u0000","aliases":[],"id":"ZLCzXpHn947bPh5owkWUwQ","name":"JUNJUN","subtype":"USER"},"type":"CREATE_IDENTITY"},"ledgerTimestamp":1653354405513,"uuid":"Yb1nbR5C60Agboo63uasXA","version":"1"}
{"action":{"alias":{"address":"N\u0000sourcecred\u0000discord\u0000MEMBER\u0000user\u0000842250665136881694\u0000","description":"discord/JUNJUN#0119"},"identityId":"ZLCzXpHn947bPh5owkWUwQ","type":"ADD_ALIAS"},"ledgerTimestamp":1653354405513,"uuid":"CQ2kOFaiBApfPzE6kFqNTQ","version":"1"}
{"action":{"identity":{"address":"N\u0000sourcecred\u0000core\u0000IDENTITY\u0000mfzzuZfqxOratzgocm8Gmw\u0000","aliases":[],"id":"mfzzuZfqxOratzgocm8Gmw","name":"michi","subtype":"USER"},"type":"CREATE_IDENTITY"},"ledgerTimestamp":1653354405513,"uuid":"1XxwEdp22oPWlpi6OgP4Ug","version":"1"}
{"action":{"alias":{"address":"N\u0000sourcecred\u0000discord\u0000MEMBER\u0000user\u0000853943720746418187\u0000","description":"discord/michi#2959"},"identityId":"mfzzuZfqxOratzgocm8Gmw","type":"ADD_ALIAS"},"ledgerTimestamp":1653354405513,"uuid":"e8GBPet6MwcJr50iNbrAJQ","version":"1"}
{"action":{"identity":{"address":"N\u0000sourcecred\u0000core\u0000IDENTITY\u0000EVMkX6h3cjYij8BokdyGrg\u0000","aliases":[],"id":"EVMkX6h3cjYij8BokdyGrg","name":"matvoxel","subtype":"USER"},"type":"CREATE_IDENTITY"},"ledgerTimestamp":1653354405514,"uuid":"rN2dPOJR48tz9rDtm0qS1Q","version":"1"}
{"action":{"alias":{"address":"N\u0000sourcecred\u0000discord\u0000MEMBER\u0000user\u0000863104240754229268\u0000","description":"discord/matvoxel#5995"},"identityId":"EVMkX6h3cjYij8BokdyGrg","type":"ADD_ALIAS"},"ledgerTimestamp":1653354405514,"uuid":"OOJV0VzxbesO3AVA2AECJA","version":"1"}
{"action":{"identity":{"address":"N\u0000sourcecred\u0000core\u0000IDENTITY\u0000dWb6gepHoAYKJUzzHpfO5A\u0000","aliases":[],"id":"dWb6gepHoAYKJUzzHpfO5A","name":"Q-A","subtype":"BOT"},"type":"CREATE_IDENTITY"},"ledgerTimestamp":1653354405514,"uuid":"CLvV6wJe8ym68eNSMjqERA","version":"1"}
{"action":{"alias":{"address":"N\u0000sourcecred\u0000discord\u0000MEMBER\u0000bot\u0000866819673906348063\u0000","description":"discord/Q-A#9475"},"identityId":"dWb6gepHoAYKJUzzHpfO5A","type":"ADD_ALIAS"},"ledgerTimestamp":1653354405514,"uuid":"snNLqAv8IntPKADeyWzxSg","version":"1"}
{"action":{"identity":{"address":"N\u0000sourcecred\u0000core\u0000IDENTITY\u00005MlX2pmH2nsO48QqW8ENUg\u0000","aliases":[],"id":"5MlX2pmH2nsO48QqW8ENUg","name":"ZEO","subtype":"USER"},"type":"CREATE_IDENTITY"},"ledgerTimestamp":1653354405514,"uuid":"61tQlYsbE5g38kNrSDMwVQ","version":"1"}
{"action":{"alias":{"address":"N\u0000sourcecred\u0000discord\u0000MEMBER\u0000user\u0000874198814754492416\u0000","description":"discord/ZEO#9345"},"identityId":"5MlX2pmH2nsO48QqW8ENUg","type":"ADD_ALIAS"},"ledgerTimestamp":1653354405514,"uuid":"OOqQM3KCzjbxdK9VGtL7kQ","version":"1"}
{"action":{"identity":{"address":"N\u0000sourcecred\u0000core\u0000IDENTITY\u0000Tgzr1x70yKMGKXnxYGBh9A\u0000","aliases":[],"id":"Tgzr1x70yKMGKXnxYGBh9A","name":"Jasonhon","subtype":"USER"},"type":"CREATE_IDENTITY"},"ledgerTimestamp":1653354405514,"uuid":"BCBGVBd7RmPH1eAtZ9szaA","version":"1"}
{"action":{"alias":{"address":"N\u0000sourcecred\u0000discord\u0000MEMBER\u0000user\u0000876244032815239208\u0000","description":"discord/Jasonhon#2491"},"identityId":"Tgzr1x70yKMGKXnxYGBh9A","type":"ADD_ALIAS"},"ledgerTimestamp":1653354405514,"uuid":"3ye55vS6hywSN9txNm9l0g","version":"1"}
{"action":{"identity":{"address":"N\u0000sourcecred\u0000core\u0000IDENTITY\u0000bzJ9NTkGidnKhVCebgNu7A\u0000","aliases":[],"id":"bzJ9NTkGidnKhVCebgNu7A","name":"Greyson","subtype":"USER"},"type":"CREATE_IDENTITY"},"ledgerTimestamp":1653354405514,"uuid":"68unUPjFdBjsovsmeGTmGQ","version":"1"}
{"action":{"alias":{"address":"N\u0000sourcecred\u0000discord\u0000MEMBER\u0000user\u0000879043210813509643\u0000","description":"discord/Greyson#8398"},"identityId":"bzJ9NTkGidnKhVCebgNu7A","type":"ADD_ALIAS"},"ledgerTimestamp":1653354405514,"uuid":"wJOQ0D7G4b4jnWHziNXqPw","version":"1"}
{"action":{"identity":{"address":"N\u0000sourcecred\u0000core\u0000IDENTITY\u0000ozDLEQOuaC8lmmGk7GGjzw\u0000","aliases":[],"id":"ozDLEQOuaC8lmmGk7GGjzw","name":"MoB","subtype":"USER"},"type":"CREATE_IDENTITY"},"ledgerTimestamp":1653354405515,"uuid":"gXkQ2p0j6vJg0dibXoSOyg","version":"1"}
{"action":{"alias":{"address":"N\u0000sourcecred\u0000discord\u0000MEMBER\u0000user\u0000884325922138894337\u0000","description":"discord/MoB#4544"},"identityId":"ozDLEQOuaC8lmmGk7GGjzw","type":"ADD_ALIAS"},"ledgerTimestamp":1653354405515,"uuid":"4nSnAdQvgJsvmLbAKwqgIA","version":"1"}
{"action":{"identity":{"address":"N\u0000sourcecred\u0000core\u0000IDENTITY\u0000I0SGM6AqMAq9mH1YwGgyAw\u0000","aliases":[],"id":"I0SGM6AqMAq9mH1YwGgyAw","name":"Yayaaaaa","subtype":"USER"},"type":"CREATE_IDENTITY"},"ledgerTimestamp":1653354405515,"uuid":"03Tqs1gYn9NNuRkBERYQ1Q","version":"1"}
{"action":{"alias":{"address":"N\u0000sourcecred\u0000discord\u0000MEMBER\u0000user\u0000888934691799982130\u0000","description":"discord/Yayaaaaa#5693"},"identityId":"I0SGM6AqMAq9mH1YwGgyAw","type":"ADD_ALIAS"},"ledgerTimestamp":1653354405515,"uuid":"ggJ558XNzIjqZ3cpL6kEHA","version":"1"}
{"action":{"identity":{"address":"N\u0000sourcecred\u0000core\u0000IDENTITY\u0000V4pbBc3gZ7B4MDwL5TznxQ\u0000","aliases":[],"id":"V4pbBc3gZ7B4MDwL5TznxQ","name":"kooly","subtype":"USER"},"type":"CREATE_IDENTITY"},"ledgerTimestamp":1653354405515,"uuid":"aH24tx0vWPZPXnDtOw7TnA","version":"1"}
{"action":{"alias":{"address":"N\u0000sourcecred\u0000discord\u0000MEMBER\u0000user\u0000892335190502936607\u0000","description":"discord/kooly#5555"},"identityId":"V4pbBc3gZ7B4MDwL5TznxQ","type":"ADD_ALIAS"},"ledgerTimestamp":1653354405515,"uuid":"H9uWEgO6VlDHefqYKI06Rw","version":"1"}
{"action":{"identity":{"address":"N\u0000sourcecred\u0000core\u0000IDENTITY\u00003DMbAE75FbTxGqTdCd9OpQ\u0000","aliases":[],"id":"3DMbAE75FbTxGqTdCd9OpQ","name":"Huang","subtype":"USER"},"type":"CREATE_IDENTITY"},"ledgerTimestamp":1653354405515,"uuid":"o9KXbKzC3Ejt7LVmQ7EV8A","version":"1"}
{"action":{"alias":{"address":"N\u0000sourcecred\u0000discord\u0000MEMBER\u0000user\u0000893108621066530837\u0000","description":"discord/Huang#4014"},"identityId":"3DMbAE75FbTxGqTdCd9OpQ","type":"ADD_ALIAS"},"ledgerTimestamp":1653354405515,"uuid":"PPBJPnlM5q5c3imzFLXYZQ","version":"1"}
{"action":{"identity":{"address":"N\u0000sourcecred\u0000core\u0000IDENTITY\u0000Bv99u5dl8srxmgMuYpsJHQ\u0000","aliases":[],"id":"Bv99u5dl8srxmgMuYpsJHQ","name":"ultramarine","subtype":"USER"},"type":"CREATE_IDENTITY"},"ledgerTimestamp":1653354405516,"uuid":"462y9IGAjFdZ3GOXtqRAyg","version":"1"}
{"action":{"alias":{"address":"N\u0000sourcecred\u0000discord\u0000MEMBER\u0000user\u0000900697249401692170\u0000","description":"discord/ultramarine#0974"},"identityId":"Bv99u5dl8srxmgMuYpsJHQ","type":"ADD_ALIAS"},"ledgerTimestamp":1653354405516,"uuid":"jKTka0Qa5AJ034FwZdzdzw","version":"1"}
{"action":{"identity":{"address":"N\u0000sourcecred\u0000core\u0000IDENTITY\u0000b0joNn0HMkUY7lDW5EuPWw\u0000","aliases":[],"id":"b0joNn0HMkUY7lDW5EuPWw","name":"0xCCandice","subtype":"USER"},"type":"CREATE_IDENTITY"},"ledgerTimestamp":1653354405516,"uuid":"8cGBJNSeYTZpG4diLf2XkQ","version":"1"}
{"action":{"alias":{"address":"N\u0000sourcecred\u0000discord\u0000MEMBER\u0000user\u0000902461346082349077\u0000","description":"discord/0xCCandice#7274"},"identityId":"b0joNn0HMkUY7lDW5EuPWw","type":"ADD_ALIAS"},"ledgerTimestamp":1653354405516,"uuid":"KMMD2NAzpBVxPnX1EGSb2Q","version":"1"}
{"action":{"identity":{"address":"N\u0000sourcecred\u0000core\u0000IDENTITY\u0000ybKRH455sJruYZT0WG3lvw\u0000","aliases":[],"id":"ybKRH455sJruYZT0WG3lvw","name":"0x-candice","subtype":"USER"},"type":"CREATE_IDENTITY"},"ledgerTimestamp":1653354405516,"uuid":"OHPNtw3uYRWYWbJxoowXIA","version":"1"}
{"action":{"alias":{"address":"N\u0000sourcecred\u0000discord\u0000MEMBER\u0000user\u0000903999334411018350\u0000","description":"discord/0x-candice#2908"},"identityId":"ybKRH455sJruYZT0WG3lvw","type":"ADD_ALIAS"},"ledgerTimestamp":1653354405516,"uuid":"PDTAMo73JIQWR0Niab5oFQ","version":"1"}
{"action":{"identity":{"address":"N\u0000sourcecred\u0000core\u0000IDENTITY\u0000Cdbim4AAkdypqSDAdKjWYQ\u0000","aliases":[],"id":"Cdbim4AAkdypqSDAdKjWYQ","name":"Heidi-Guo","subtype":"USER"},"type":"CREATE_IDENTITY"},"ledgerTimestamp":1653354405516,"uuid":"XBwDSayIJQX3syW6Abgbxg","version":"1"}
{"action":{"alias":{"address":"N\u0000sourcecred\u0000discord\u0000MEMBER\u0000user\u0000905360973727150111\u0000","description":"discord/Heidi-Guo#2154"},"identityId":"Cdbim4AAkdypqSDAdKjWYQ","type":"ADD_ALIAS"},"ledgerTimestamp":1653354405517,"uuid":"pA1rFzrA85Mtg73Mqk65IA","version":"1"}
{"action":{"identity":{"address":"N\u0000sourcecred\u0000core\u0000IDENTITY\u0000k09vpc1qE76aUezeLohvaw\u0000","aliases":[],"id":"k09vpc1qE76aUezeLohvaw","name":"Og","subtype":"USER"},"type":"CREATE_IDENTITY"},"ledgerTimestamp":1653354405517,"uuid":"p8013HpT9b3pmPROjaUm1w","version":"1"}
{"action":{"alias":{"address":"N\u0000sourcecred\u0000discord\u0000MEMBER\u0000user\u0000907259848520003605\u0000","description":"discord/Og#1963"},"identityId":"k09vpc1qE76aUezeLohvaw","type":"ADD_ALIAS"},"ledgerTimestamp":1653354405517,"uuid":"xwa8tQXmK2kjX6rm2yjWPA","version":"1"}
{"action":{"identity":{"address":"N\u0000sourcecred\u0000core\u0000IDENTITY\u0000W6cgr7N02TZfLyq5N4OPLQ\u0000","aliases":[],"id":"W6cgr7N02TZfLyq5N4OPLQ","name":"Anyyyyy","subtype":"USER"},"type":"CREATE_IDENTITY"},"ledgerTimestamp":1653354405517,"uuid":"g62ubkqCbmtYU2eF5DJB8g","version":"1"}
{"action":{"alias":{"address":"N\u0000sourcecred\u0000discord\u0000MEMBER\u0000user\u0000907576754628087848\u0000","description":"discord/Anyyyyy#4228"},"identityId":"W6cgr7N02TZfLyq5N4OPLQ","type":"ADD_ALIAS"},"ledgerTimestamp":1653354405517,"uuid":"Je7knF4ogV7wHm8LFDJyFw","version":"1"}
{"action":{"identity":{"address":"N\u0000sourcecred\u0000core\u0000IDENTITY\u00005BEtRZvnC974LuRYEqzyig\u0000","aliases":[],"id":"5BEtRZvnC974LuRYEqzyig","name":"easyEE","subtype":"USER"},"type":"CREATE_IDENTITY"},"ledgerTimestamp":1653354405517,"uuid":"fOtlJ4VWWESdKOF9hbA8Dg","version":"1"}
{"action":{"alias":{"address":"N\u0000sourcecred\u0000discord\u0000MEMBER\u0000user\u0000916786980652736563\u0000","description":"discord/easyEE#7549"},"identityId":"5BEtRZvnC974LuRYEqzyig","type":"ADD_ALIAS"},"ledgerTimestamp":1653354405517,"uuid":"5aJtyCOnDFJmsge9EerS3g","version":"1"}
{"action":{"identity":{"address":"N\u0000sourcecred\u0000core\u0000IDENTITY\u00001VRc8SzrxLOlROY3Mt1vyQ\u0000","aliases":[],"id":"1VRc8SzrxLOlROY3Mt1vyQ","name":"MIX-Studio-Rina","subtype":"USER"},"type":"CREATE_IDENTITY"},"ledgerTimestamp":1653354405518,"uuid":"3HPb3ghqVLedDEWKMtyXkg","version":"1"}
{"action":{"alias":{"address":"N\u0000sourcecred\u0000discord\u0000MEMBER\u0000user\u0000917971028712521788\u0000","description":"discord/MIX-Studio-Rina#4920"},"identityId":"1VRc8SzrxLOlROY3Mt1vyQ","type":"ADD_ALIAS"},"ledgerTimestamp":1653354405518,"uuid":"bxKAt50Bo07MCxToug9j3w","version":"1"}
{"action":{"identity":{"address":"N\u0000sourcecred\u0000core\u0000IDENTITY\u0000R7qVXcXlZ3Y97uY2yozYXw\u0000","aliases":[],"id":"R7qVXcXlZ3Y97uY2yozYXw","name":"MuTsing","subtype":"USER"},"type":"CREATE_IDENTITY"},"ledgerTimestamp":1653354405518,"uuid":"hXoRP3iG96lp0mkJwR1oJg","version":"1"}
{"action":{"alias":{"address":"N\u0000sourcecred\u0000discord\u0000MEMBER\u0000user\u0000919424472140886082\u0000","description":"discord/MuTsing#4663"},"identityId":"R7qVXcXlZ3Y97uY2yozYXw","type":"ADD_ALIAS"},"ledgerTimestamp":1653354405518,"uuid":"IqUygbr7JNhgQwai6rE8KA","version":"1"}
{"action":{"identity":{"address":"N\u0000sourcecred\u0000core\u0000IDENTITY\u0000ac41N51WgGjizytRWzZZgA\u0000","aliases":[],"id":"ac41N51WgGjizytRWzZZgA","name":"Eric520","subtype":"USER"},"type":"CREATE_IDENTITY"},"ledgerTimestamp":1653354405518,"uuid":"7MoeS5qU2Kvlx6rOvr12QA","version":"1"}
{"action":{"alias":{"address":"N\u0000sourcecred\u0000discord\u0000MEMBER\u0000user\u0000920331703048863744\u0000","description":"discord/Eric520#5731"},"identityId":"ac41N51WgGjizytRWzZZgA","type":"ADD_ALIAS"},"ledgerTimestamp":1653354405518,"uuid":"NFRb4tvaqLw8cr8vLNvfYw","version":"1"}
{"action":{"identity":{"address":"N\u0000sourcecred\u0000core\u0000IDENTITY\u0000K53DySoK7iEoVXhDQNbzew\u0000","aliases":[],"id":"K53DySoK7iEoVXhDQNbzew","name":"jnz20220222","subtype":"USER"},"type":"CREATE_IDENTITY"},"ledgerTimestamp":1653354405518,"uuid":"9tolhNdFJOFKAIJaH4ywBQ","version":"1"}
{"action":{"alias":{"address":"N\u0000sourcecred\u0000discord\u0000MEMBER\u0000user\u0000920709311028678666\u0000","description":"discord/jnz20220222#0962"},"identityId":"K53DySoK7iEoVXhDQNbzew","type":"ADD_ALIAS"},"ledgerTimestamp":1653354405518,"uuid":"HooK3bSB4T9KKF7i226MrA","version":"1"}
{"action":{"identity":{"address":"N\u0000sourcecred\u0000core\u0000IDENTITY\u0000oH0OSp2UqKM8uqrJmnNsvA\u0000","aliases":[],"id":"oH0OSp2UqKM8uqrJmnNsvA","name":"Blender66-","subtype":"USER"},"type":"CREATE_IDENTITY"},"ledgerTimestamp":1653354405519,"uuid":"3jD1XQFRM3aZiQUxeTOijg","version":"1"}
{"action":{"alias":{"address":"N\u0000sourcecred\u0000discord\u0000MEMBER\u0000user\u0000921365177088229416\u0000","description":"discord/Blender66-#3083"},"identityId":"oH0OSp2UqKM8uqrJmnNsvA","type":"ADD_ALIAS"},"ledgerTimestamp":1653354405519,"uuid":"zMXnLG4LVLn6n9ZHmcb3tw","version":"1"}
{"action":{"identity":{"address":"N\u0000sourcecred\u0000core\u0000IDENTITY\u0000xobTxdNuK1N3irhg2uO8Ow\u0000","aliases":[],"id":"xobTxdNuK1N3irhg2uO8Ow","name":"SlimeDL","subtype":"USER"},"type":"CREATE_IDENTITY"},"ledgerTimestamp":1653354405519,"uuid":"BMgx7hb0iel4CBigcnnLaQ","version":"1"}
{"action":{"alias":{"address":"N\u0000sourcecred\u0000discord\u0000MEMBER\u0000user\u0000922349063880450108\u0000","description":"discord/SlimeDL#5521"},"identityId":"xobTxdNuK1N3irhg2uO8Ow","type":"ADD_ALIAS"},"ledgerTimestamp":1653354405519,"uuid":"MWMR7sKEfZdB3M1miO6gfg","version":"1"}
{"action":{"identity":{"address":"N\u0000sourcecred\u0000core\u0000IDENTITY\u0000kBm8EZjzgoVkupPgVTl9Dw\u0000","aliases":[],"id":"kBm8EZjzgoVkupPgVTl9Dw","name":"SLLLO","subtype":"USER"},"type":"CREATE_IDENTITY"},"ledgerTimestamp":1653354405519,"uuid":"kOB9BpopTqbvMDJMwj9y1g","version":"1"}
{"action":{"alias":{"address":"N\u0000sourcecred\u0000discord\u0000MEMBER\u0000user\u0000923620146856222750\u0000","description":"discord/SLLLO#3865"},"identityId":"kBm8EZjzgoVkupPgVTl9Dw","type":"ADD_ALIAS"},"ledgerTimestamp":1653354405519,"uuid":"hlOVMN3EdAL4olQiONdW7w","version":"1"}
{"action":{"identity":{"address":"N\u0000sourcecred\u0000core\u0000IDENTITY\u00009ly4YG5eB15zz4XDKzfLDQ\u0000","aliases":[],"id":"9ly4YG5eB15zz4XDKzfLDQ","name":"Gesture-Arch","subtype":"USER"},"type":"CREATE_IDENTITY"},"ledgerTimestamp":1653354405520,"uuid":"gH1nbTdglvVx0GmB5aPvKw","version":"1"}
{"action":{"alias":{"address":"N\u0000sourcecred\u0000discord\u0000MEMBER\u0000user\u0000925520929457569832\u0000","description":"discord/Gesture-Arch#0866"},"identityId":"9ly4YG5eB15zz4XDKzfLDQ","type":"ADD_ALIAS"},"ledgerTimestamp":1653354405520,"uuid":"MeLEbl0UY67CqrNGk5JBdQ","version":"1"}
{"action":{"identity":{"address":"N\u0000sourcecred\u0000core\u0000IDENTITY\u0000uV7NJrNwhNoJpeGWjgp0fQ\u0000","aliases":[],"id":"uV7NJrNwhNoJpeGWjgp0fQ","name":"perfeccionistas","subtype":"USER"},"type":"CREATE_IDENTITY"},"ledgerTimestamp":1653354405520,"uuid":"39WC5APdYXnD3W2a5ND8jw","version":"1"}
{"action":{"alias":{"address":"N\u0000sourcecred\u0000discord\u0000MEMBER\u0000user\u0000932845502842691584\u0000","description":"discord/perfeccionistas#3903"},"identityId":"uV7NJrNwhNoJpeGWjgp0fQ","type":"ADD_ALIAS"},"ledgerTimestamp":1653354405520,"uuid":"p2XW3AD6aoB7t2d248yRVw","version":"1"}
{"action":{"identity":{"address":"N\u0000sourcecred\u0000core\u0000IDENTITY\u00008D4V2N8F8U8y5q0zOw1NVQ\u0000","aliases":[],"id":"8D4V2N8F8U8y5q0zOw1NVQ","name":"Junie","subtype":"USER"},"type":"CREATE_IDENTITY"},"ledgerTimestamp":1653354405520,"uuid":"uBk7MxKMBye9GpDUBjXnCw","version":"1"}
{"action":{"alias":{"address":"N\u0000sourcecred\u0000discord\u0000MEMBER\u0000user\u0000939107261400358923\u0000","description":"discord/Junie#5438"},"identityId":"8D4V2N8F8U8y5q0zOw1NVQ","type":"ADD_ALIAS"},"ledgerTimestamp":1653354405520,"uuid":"gDiM6GYGYMEk37se1Rx2NA","version":"1"}
{"action":{"identity":{"address":"N\u0000sourcecred\u0000core\u0000IDENTITY\u0000LMNsA4fdF2bt3vzfBWd0gw\u0000","aliases":[],"id":"LMNsA4fdF2bt3vzfBWd0gw","name":"goldhwa","subtype":"USER"},"type":"CREATE_IDENTITY"},"ledgerTimestamp":1653354405521,"uuid":"CvjbwdLEZzOw0VmNjNpOzw","version":"1"}
{"action":{"alias":{"address":"N\u0000sourcecred\u0000discord\u0000MEMBER\u0000user\u0000944551365911392297\u0000","description":"discord/goldhwa#5430"},"identityId":"LMNsA4fdF2bt3vzfBWd0gw","type":"ADD_ALIAS"},"ledgerTimestamp":1653354405521,"uuid":"5xULuA8BB0FwIyDTdKqt6Q","version":"1"}
{"action":{"identity":{"address":"N\u0000sourcecred\u0000core\u0000IDENTITY\u0000E8x3k6ygiQh8n7iQh0FKtg\u0000","aliases":[],"id":"E8x3k6ygiQh8n7iQh0FKtg","name":"LIKEU","subtype":"USER"},"type":"CREATE_IDENTITY"},"ledgerTimestamp":1653354405521,"uuid":"M6OgSL0rM42c9U9gqzxgvg","version":"1"}
{"action":{"alias":{"address":"N\u0000sourcecred\u0000discord\u0000MEMBER\u0000user\u0000946436198312845312\u0000","description":"discord/LIKEU#1339"},"identityId":"E8x3k6ygiQh8n7iQh0FKtg","type":"ADD_ALIAS"},"ledgerTimestamp":1653354405521,"uuid":"Xbc17a27UMUyVxz9y5IqRA","version":"1"}
{"action":{"identity":{"address":"N\u0000sourcecred\u0000core\u0000IDENTITY\u0000Y5o9v1jgE84wCXteBja0og\u0000","aliases":[],"id":"Y5o9v1jgE84wCXteBja0og","name":"YUWA","subtype":"USER"},"type":"CREATE_IDENTITY"},"ledgerTimestamp":1653354405521,"uuid":"Zuxxf4YvhnRqEyYsnCEbYg","version":"1"}
{"action":{"alias":{"address":"N\u0000sourcecred\u0000discord\u0000MEMBER\u0000user\u0000947013829596950539\u0000","description":"discord/YUWA#4928"},"identityId":"Y5o9v1jgE84wCXteBja0og","type":"ADD_ALIAS"},"ledgerTimestamp":1653354405521,"uuid":"3wMqOZNOl7ZPpkrEg94WBA","version":"1"}
{"action":{"identity":{"address":"N\u0000sourcecred\u0000core\u0000IDENTITY\u0000kRe5jK7ZUpdP2gOMpNo5Lw\u0000","aliases":[],"id":"kRe5jK7ZUpdP2gOMpNo5Lw","name":"fayism","subtype":"USER"},"type":"CREATE_IDENTITY"},"ledgerTimestamp":1653354405521,"uuid":"DqMpCEc6twQu8vBNA8Jesw","version":"1"}
{"action":{"alias":{"address":"N\u0000sourcecred\u0000discord\u0000MEMBER\u0000user\u0000949205738385977394\u0000","description":"discord/fayism#8756"},"identityId":"kRe5jK7ZUpdP2gOMpNo5Lw","type":"ADD_ALIAS"},"ledgerTimestamp":1653354405521,"uuid":"jPu3mgRYuyum98R7LUd6ew","version":"1"}
{"action":{"identity":{"address":"N\u0000sourcecred\u0000core\u0000IDENTITY\u0000z4ODKJkeirt97CaqYyW5cQ\u0000","aliases":[],"id":"z4ODKJkeirt97CaqYyW5cQ","name":"seanwang","subtype":"USER"},"type":"CREATE_IDENTITY"},"ledgerTimestamp":1653354405521,"uuid":"keWHr96LmBYns3VOXMB2eQ","version":"1"}
{"action":{"alias":{"address":"N\u0000sourcecred\u0000discord\u0000MEMBER\u0000user\u0000949216846475841557\u0000","description":"discord/seanwang#8318"},"identityId":"z4ODKJkeirt97CaqYyW5cQ","type":"ADD_ALIAS"},"ledgerTimestamp":1653354405522,"uuid":"un85MNLrtM1uA3ZwWQV77w","version":"1"}
{"action":{"identity":{"address":"N\u0000sourcecred\u0000core\u0000IDENTITY\u0000IPjcDl1qLzNMC0UpD2FzpA\u0000","aliases":[],"id":"IPjcDl1qLzNMC0UpD2FzpA","name":"JadeWu","subtype":"USER"},"type":"CREATE_IDENTITY"},"ledgerTimestamp":1653354405522,"uuid":"2WhQypCxnVevs4J9q0grhw","version":"1"}
{"action":{"alias":{"address":"N\u0000sourcecred\u0000discord\u0000MEMBER\u0000user\u0000950715539355992144\u0000","description":"discord/JadeWu#5252"},"identityId":"IPjcDl1qLzNMC0UpD2FzpA","type":"ADD_ALIAS"},"ledgerTimestamp":1653354405522,"uuid":"eaoF2eNcDP0ERTRzxSzqnA","version":"1"}
{"action":{"identity":{"address":"N\u0000sourcecred\u0000core\u0000IDENTITY\u0000penhJbAUpGYcoXgG7Mv05w\u0000","aliases":[],"id":"penhJbAUpGYcoXgG7Mv05w","name":"Nitrogen-Morris","subtype":"USER"},"type":"CREATE_IDENTITY"},"ledgerTimestamp":1653354405522,"uuid":"TyKDMa1AgsXMpe6fWL9UvA","version":"1"}
{"action":{"alias":{"address":"N\u0000sourcecred\u0000discord\u0000MEMBER\u0000user\u0000952988815105073152\u0000","description":"discord/Nitrogen-Morris#9462"},"identityId":"penhJbAUpGYcoXgG7Mv05w","type":"ADD_ALIAS"},"ledgerTimestamp":1653354405522,"uuid":"p9Ox0gkpjp2QjntR0LNzgw","version":"1"}
{"action":{"identity":{"address":"N\u0000sourcecred\u0000core\u0000IDENTITY\u0000PwT9891z2PT1soNkB0lafQ\u0000","aliases":[],"id":"PwT9891z2PT1soNkB0lafQ","name":"discord-954292056912703538","subtype":"USER"},"type":"CREATE_IDENTITY"},"ledgerTimestamp":1653354405523,"uuid":"5wDF911rezJKX9roiBt14g","version":"1"}
{"action":{"alias":{"address":"N\u0000sourcecred\u0000discord\u0000MEMBER\u0000user\u0000954292056912703538\u0000","description":"discord/discord-954292056912703538#9474"},"identityId":"PwT9891z2PT1soNkB0lafQ","type":"ADD_ALIAS"},"ledgerTimestamp":1653354405523,"uuid":"NNGDxsZ0xn4ObwIg6bmH8Q","version":"1"}
{"action":{"identity":{"address":"N\u0000sourcecred\u0000core\u0000IDENTITY\u0000L1gu1PskvZNqAJfge1J4UA\u0000","aliases":[],"id":"L1gu1PskvZNqAJfge1J4UA","name":"Dongxingy","subtype":"USER"},"type":"CREATE_IDENTITY"},"ledgerTimestamp":1653354405523,"uuid":"rbrqweHoer7W0Q3NKJGiPQ","version":"1"}
{"action":{"alias":{"address":"N\u0000sourcecred\u0000discord\u0000MEMBER\u0000user\u0000955364998283137024\u0000","description":"discord/Dongxingy#0639"},"identityId":"L1gu1PskvZNqAJfge1J4UA","type":"ADD_ALIAS"},"ledgerTimestamp":1653354405523,"uuid":"jdxUjeGsnyJybPu2tBzA6Q","version":"1"}
{"action":{"identity":{"address":"N\u0000sourcecred\u0000core\u0000IDENTITY\u00008zM07YF7wbt3npf2Y9xn8A\u0000","aliases":[],"id":"8zM07YF7wbt3npf2Y9xn8A","name":"Lynn-","subtype":"USER"},"type":"CREATE_IDENTITY"},"ledgerTimestamp":1653354405523,"uuid":"S5oyPhQWdN7Jy7QyWPX5Qg","version":"1"}
{"action":{"alias":{"address":"N\u0000sourcecred\u0000discord\u0000MEMBER\u0000user\u0000955673055076696097\u0000","description":"discord/Lynn-#0497"},"identityId":"8zM07YF7wbt3npf2Y9xn8A","type":"ADD_ALIAS"},"ledgerTimestamp":1653354405523,"uuid":"pHPK6CAIJPAtDxdIaL44Ew","version":"1"}
{"action":{"identity":{"address":"N\u0000sourcecred\u0000core\u0000IDENTITY\u0000aehJtQdLheCl8RTKv6JNtQ\u0000","aliases":[],"id":"aehJtQdLheCl8RTKv6JNtQ","name":"Meraki","subtype":"USER"},"type":"CREATE_IDENTITY"},"ledgerTimestamp":1653354405524,"uuid":"03pJDRyaq8VUWzZUxyVMVQ","version":"1"}
{"action":{"alias":{"address":"N\u0000sourcecred\u0000discord\u0000MEMBER\u0000user\u0000957092733519020092\u0000","description":"discord/Meraki#5378"},"identityId":"aehJtQdLheCl8RTKv6JNtQ","type":"ADD_ALIAS"},"ledgerTimestamp":1653354405524,"uuid":"N5aZWavZpCyIaXUb1OSz7Q","version":"1"}
{"action":{"identity":{"address":"N\u0000sourcecred\u0000core\u0000IDENTITY\u0000QbbZvB9ivPeYWVcwOB8vdQ\u0000","aliases":[],"id":"QbbZvB9ivPeYWVcwOB8vdQ","name":"Coke0x","subtype":"USER"},"type":"CREATE_IDENTITY"},"ledgerTimestamp":1653354405524,"uuid":"Kmm8Bo4jBqI0FNuMXR03Kw","version":"1"}
{"action":{"alias":{"address":"N\u0000sourcecred\u0000discord\u0000MEMBER\u0000user\u0000957985608637247518\u0000","description":"discord/Coke0x#6666"},"identityId":"QbbZvB9ivPeYWVcwOB8vdQ","type":"ADD_ALIAS"},"ledgerTimestamp":1653354405524,"uuid":"1WiEkFBI7Qz6G8RaT6zigQ","version":"1"}
{"action":{"identity":{"address":"N\u0000sourcecred\u0000core\u0000IDENTITY\u0000I2BSEiZWeI63q5M7JMFxtg\u0000","aliases":[],"id":"I2BSEiZWeI63q5M7JMFxtg","name":"Stacy-Wonderbee","subtype":"USER"},"type":"CREATE_IDENTITY"},"ledgerTimestamp":1653354405525,"uuid":"oImBXN33zZhAtgRx0F8XPg","version":"1"}
{"action":{"alias":{"address":"N\u0000sourcecred\u0000discord\u0000MEMBER\u0000user\u0000958001997091594320\u0000","description":"discord/Stacy-Wonderbee#7189"},"identityId":"I2BSEiZWeI63q5M7JMFxtg","type":"ADD_ALIAS"},"ledgerTimestamp":1653354405525,"uuid":"1V1vOpPVEmpok0J3958BCw","version":"1"}
{"action":{"identity":{"address":"N\u0000sourcecred\u0000core\u0000IDENTITY\u0000YaiKawHg8kVK3bq1vOhwPQ\u0000","aliases":[],"id":"YaiKawHg8kVK3bq1vOhwPQ","name":"discord-958068980956921896","subtype":"USER"},"type":"CREATE_IDENTITY"},"ledgerTimestamp":1653354405525,"uuid":"zuPxQbzDNvLgof1a849P6w","version":"1"}
{"action":{"alias":{"address":"N\u0000sourcecred\u0000discord\u0000MEMBER\u0000user\u0000958068980956921896\u0000","description":"discord/discord-958068980956921896#5561"},"identityId":"YaiKawHg8kVK3bq1vOhwPQ","type":"ADD_ALIAS"},"ledgerTimestamp":1653354405525,"uuid":"yPqlvnWhGoRyEQxq1irCpg","version":"1"}
{"action":{"identity":{"address":"N\u0000sourcecred\u0000core\u0000IDENTITY\u0000UlRiyVOZdPQiANys0B99Xw\u0000","aliases":[],"id":"UlRiyVOZdPQiANys0B99Xw","name":"X-Simon","subtype":"USER"},"type":"CREATE_IDENTITY"},"ledgerTimestamp":1653354405525,"uuid":"KT0YhzaydwilROnWDSWIdw","version":"1"}
{"action":{"alias":{"address":"N\u0000sourcecred\u0000discord\u0000MEMBER\u0000user\u0000959287844508147772\u0000","description":"discord/X-Simon#8069"},"identityId":"UlRiyVOZdPQiANys0B99Xw","type":"ADD_ALIAS"},"ledgerTimestamp":1653354405525,"uuid":"yapV12ZiZs5XLBmUXip5NA","version":"1"}
{"action":{"identity":{"address":"N\u0000sourcecred\u0000core\u0000IDENTITY\u0000k997edgbzq2BcAgtOjZNng\u0000","aliases":[],"id":"k997edgbzq2BcAgtOjZNng","name":"SimonX","subtype":"USER"},"type":"CREATE_IDENTITY"},"ledgerTimestamp":1653354405525,"uuid":"30Ir6Ws5yzAETzrg4UejUA","version":"1"}
{"action":{"alias":{"address":"N\u0000sourcecred\u0000discord\u0000MEMBER\u0000user\u0000959291631574589491\u0000","description":"discord/SimonX#9081"},"identityId":"k997edgbzq2BcAgtOjZNng","type":"ADD_ALIAS"},"ledgerTimestamp":1653354405525,"uuid":"sGM24kE2di7DvV76mvDr5g","version":"1"}
{"action":{"identity":{"address":"N\u0000sourcecred\u0000core\u0000IDENTITY\u0000QgkCq6Ac2PB4WuAi48WZHA\u0000","aliases":[],"id":"QgkCq6Ac2PB4WuAi48WZHA","name":"metaorange","subtype":"USER"},"type":"CREATE_IDENTITY"},"ledgerTimestamp":1653354405526,"uuid":"J2vqoJHpqRLtlAQ9KKEp7A","version":"1"}
{"action":{"alias":{"address":"N\u0000sourcecred\u0000discord\u0000MEMBER\u0000user\u0000959839473783422996\u0000","description":"discord/metaorange#6206"},"identityId":"QgkCq6Ac2PB4WuAi48WZHA","type":"ADD_ALIAS"},"ledgerTimestamp":1653354405526,"uuid":"Qix9qkq4Y7aBhjNBTEXhJQ","version":"1"}
{"action":{"identity":{"address":"N\u0000sourcecred\u0000core\u0000IDENTITY\u0000x511Y0Ce6nVyi0QHGJxyiw\u0000","aliases":[],"id":"x511Y0Ce6nVyi0QHGJxyiw","name":"cooky","subtype":"USER"},"type":"CREATE_IDENTITY"},"ledgerTimestamp":1653354405526,"uuid":"Yw5e8uemi0Yq3CA6LC7s7A","version":"1"}
{"action":{"alias":{"address":"N\u0000sourcecred\u0000discord\u0000MEMBER\u0000user\u0000960580331688321104\u0000","description":"discord/cooky#5644"},"identityId":"x511Y0Ce6nVyi0QHGJxyiw","type":"ADD_ALIAS"},"ledgerTimestamp":1653354405526,"uuid":"TY8S4dEeg7uvfmerz8adkw","version":"1"}
{"action":{"identity":{"address":"N\u0000sourcecred\u0000core\u0000IDENTITY\u0000Yey8y8imcvCmpEw3FdhQNg\u0000","aliases":[],"id":"Yey8y8imcvCmpEw3FdhQNg","name":"czp","subtype":"USER"},"type":"CREATE_IDENTITY"},"ledgerTimestamp":1653354405527,"uuid":"0Dn883mLohqk6YrE5KFdvw","version":"1"}
{"action":{"alias":{"address":"N\u0000sourcecred\u0000discord\u0000MEMBER\u0000user\u0000963088575124111391\u0000","description":"discord/czp#5651"},"identityId":"Yey8y8imcvCmpEw3FdhQNg","type":"ADD_ALIAS"},"ledgerTimestamp":1653354405527,"uuid":"oPMYCn4LlTRla3NWtex3Hg","version":"1"}
{"action":{"identity":{"address":"N\u0000sourcecred\u0000core\u0000IDENTITY\u0000Gk2oMJ3TnFxaLdBmljQEFg\u0000","aliases":[],"id":"Gk2oMJ3TnFxaLdBmljQEFg","name":"S-J","subtype":"USER"},"type":"CREATE_IDENTITY"},"ledgerTimestamp":1653354405527,"uuid":"qsZXCkpQgoxuwr4RsoWOGg","version":"1"}
{"action":{"alias":{"address":"N\u0000sourcecred\u0000discord\u0000MEMBER\u0000user\u0000964087160686927902\u0000","description":"discord/S-J#4622"},"identityId":"Gk2oMJ3TnFxaLdBmljQEFg","type":"ADD_ALIAS"},"ledgerTimestamp":1653354405527,"uuid":"DosEpJFpq8TlJURNsGmAMw","version":"1"}
{"action":{"identity":{"address":"N\u0000sourcecred\u0000core\u0000IDENTITY\u0000WNJi1RYFJAZanS0G1Vy2GA\u0000","aliases":[],"id":"WNJi1RYFJAZanS0G1Vy2GA","name":"MUA-Servant","subtype":"BOT"},"type":"CREATE_IDENTITY"},"ledgerTimestamp":1653354405527,"uuid":"sBbxGDZjz6xRDoszBoj3WA","version":"1"}
{"action":{"alias":{"address":"N\u0000sourcecred\u0000discord\u0000MEMBER\u0000bot\u0000964421665570316318\u0000","description":"discord/MUA-Servant#6542"},"identityId":"WNJi1RYFJAZanS0G1Vy2GA","type":"ADD_ALIAS"},"ledgerTimestamp":1653354405527,"uuid":"8gANV48rYI8jqJLg6ZzmUA","version":"1"}
{"action":{"identity":{"address":"N\u0000sourcecred\u0000core\u0000IDENTITY\u0000HqgG0hd9dZjDqwd4rOzqcA\u0000","aliases":[],"id":"HqgG0hd9dZjDqwd4rOzqcA","name":"M-Left","subtype":"USER"},"type":"CREATE_IDENTITY"},"ledgerTimestamp":1653354405527,"uuid":"du00Q4Z10yoWXAd8f1wOug","version":"1"}
{"action":{"alias":{"address":"N\u0000sourcecred\u0000discord\u0000MEMBER\u0000user\u0000965652490009854052\u0000","description":"discord/M-Left#9181"},"identityId":"HqgG0hd9dZjDqwd4rOzqcA","type":"ADD_ALIAS"},"ledgerTimestamp":1653354405527,"uuid":"GT47Bxvn7ywTpyOfgYMjSQ","version":"1"}
{"action":{"identity":{"address":"N\u0000sourcecred\u0000core\u0000IDENTITY\u0000qzGvrtdK908ENVZm4aXOYw\u0000","aliases":[],"id":"qzGvrtdK908ENVZm4aXOYw","name":"M-LEFT-discord","subtype":"USER"},"type":"CREATE_IDENTITY"},"ledgerTimestamp":1653354405528,"uuid":"0tpxEVnRPgmJf5TL5JOqjg","version":"1"}
{"action":{"alias":{"address":"N\u0000sourcecred\u0000discord\u0000MEMBER\u0000user\u0000966256743959105576\u0000","description":"discord/M-LEFT#2311"},"identityId":"qzGvrtdK908ENVZm4aXOYw","type":"ADD_ALIAS"},"ledgerTimestamp":1653354405528,"uuid":"2yrO3gFoFQznFxOU8v7Fkw","version":"1"}
{"action":{"identity":{"address":"N\u0000sourcecred\u0000core\u0000IDENTITY\u0000Oh3EBCzJYai1sohrp13KYA\u0000","aliases":[],"id":"Oh3EBCzJYai1sohrp13KYA","name":"Wjz451935154","subtype":"USER"},"type":"CREATE_IDENTITY"},"ledgerTimestamp":1653354405528,"uuid":"0TQ4RFVqTwlAeu0LGRkm0Q","version":"1"}
{"action":{"alias":{"address":"N\u0000sourcecred\u0000discord\u0000MEMBER\u0000user\u0000966290932192399430\u0000","description":"discord/Wjz451935154#9805"},"identityId":"Oh3EBCzJYai1sohrp13KYA","type":"ADD_ALIAS"},"ledgerTimestamp":1653354405528,"uuid":"gGG2Mwzj12rJWGBMCpj36A","version":"1"}
{"action":{"identity":{"address":"N\u0000sourcecred\u0000core\u0000IDENTITY\u0000CddXjveZebk63yxw1VT0Iw\u0000","aliases":[],"id":"CddXjveZebk63yxw1VT0Iw","name":"Amo","subtype":"USER"},"type":"CREATE_IDENTITY"},"ledgerTimestamp":1653354405528,"uuid":"e499ZNxum2GSGXxsKO4EMQ","version":"1"}
{"action":{"alias":{"address":"N\u0000sourcecred\u0000discord\u0000MEMBER\u0000user\u0000967472359642661015\u0000","description":"discord/Amo#3151"},"identityId":"CddXjveZebk63yxw1VT0Iw","type":"ADD_ALIAS"},"ledgerTimestamp":1653354405529,"uuid":"wv2L1FKf1OImjeFRqUrcJg","version":"1"}
{"action":{"identity":{"address":"N\u0000sourcecred\u0000core\u0000IDENTITY\u0000hrePv6r13KBXx0ruOc7cRA\u0000","aliases":[],"id":"hrePv6r13KBXx0ruOc7cRA","name":"Pathiu","subtype":"USER"},"type":"CREATE_IDENTITY"},"ledgerTimestamp":1653354405529,"uuid":"2V5lVIGvWN1czbggxBR6mA","version":"1"}
{"action":{"alias":{"address":"N\u0000sourcecred\u0000discord\u0000MEMBER\u0000user\u0000967807319222149180\u0000","description":"discord/Pathiu#5308"},"identityId":"hrePv6r13KBXx0ruOc7cRA","type":"ADD_ALIAS"},"ledgerTimestamp":1653354405529,"uuid":"mLuQ8quylvT239IEgO2tBQ","version":"1"}
{"action":{"identity":{"address":"N\u0000sourcecred\u0000core\u0000IDENTITY\u0000dGMniZ8eWk4rJEEBWDRMFw\u0000","aliases":[],"id":"dGMniZ8eWk4rJEEBWDRMFw","name":"Juneeeee","subtype":"USER"},"type":"CREATE_IDENTITY"},"ledgerTimestamp":1653354405530,"uuid":"v3NlXbYVP3bQi3NzjBKloQ","version":"1"}
{"action":{"alias":{"address":"N\u0000sourcecred\u0000discord\u0000MEMBER\u0000user\u0000967978617458004008\u0000","description":"discord/Juneeeee#9260"},"identityId":"dGMniZ8eWk4rJEEBWDRMFw","type":"ADD_ALIAS"},"ledgerTimestamp":1653354405530,"uuid":"r917oEnMfYCRQXIONw3ACQ","version":"1"}
{"action":{"identity":{"address":"N\u0000sourcecred\u0000core\u0000IDENTITY\u0000B4BfmS3iVIljZP9qLEM9aw\u0000","aliases":[],"id":"B4BfmS3iVIljZP9qLEM9aw","name":"iadlk-MUA","subtype":"USER"},"type":"CREATE_IDENTITY"},"ledgerTimestamp":1653354405530,"uuid":"hy9deBkJV2Ybce2cP7X8jw","version":"1"}
{"action":{"alias":{"address":"N\u0000sourcecred\u0000discord\u0000MEMBER\u0000user\u0000968453988892680223\u0000","description":"discord/iadlk-MUA#8188"},"identityId":"B4BfmS3iVIljZP9qLEM9aw","type":"ADD_ALIAS"},"ledgerTimestamp":1653354405530,"uuid":"x3BLXBIBWZ7DKiD1SOjyLw","version":"1"}
{"action":{"identity":{"address":"N\u0000sourcecred\u0000core\u0000IDENTITY\u0000iWcA3clMVOqkppKgj9lyXQ\u0000","aliases":[],"id":"iWcA3clMVOqkppKgj9lyXQ","name":"Wennie","subtype":"USER"},"type":"CREATE_IDENTITY"},"ledgerTimestamp":1653354405531,"uuid":"3TJg71BsjhgH1tVyuA3BbA","version":"1"}
{"action":{"alias":{"address":"N\u0000sourcecred\u0000discord\u0000MEMBER\u0000user\u0000969191664574922752\u0000","description":"discord/Wennie#9940"},"identityId":"iWcA3clMVOqkppKgj9lyXQ","type":"ADD_ALIAS"},"ledgerTimestamp":1653354405531,"uuid":"2VtASYRRJuYPnPJET9ep4g","version":"1"}
{"action":{"identity":{"address":"N\u0000sourcecred\u0000core\u0000IDENTITY\u0000CKH25yBQSBPSm4wLRWQFwA\u0000","aliases":[],"id":"CKH25yBQSBPSm4wLRWQFwA","name":"Wennie-discord","subtype":"USER"},"type":"CREATE_IDENTITY"},"ledgerTimestamp":1653354405531,"uuid":"N3JqZjfQT1EH7wHdMYziJQ","version":"1"}
{"action":{"alias":{"address":"N\u0000sourcecred\u0000discord\u0000MEMBER\u0000user\u0000969195293344161882\u0000","description":"discord/Wennie#9361"},"identityId":"CKH25yBQSBPSm4wLRWQFwA","type":"ADD_ALIAS"},"ledgerTimestamp":1653354405531,"uuid":"KxBhAsbf65MRBdx1nr934A","version":"1"}
{"action":{"identity":{"address":"N\u0000sourcecred\u0000core\u0000IDENTITY\u00003eMaieRQa5vpMtj3aN8kBw\u0000","aliases":[],"id":"3eMaieRQa5vpMtj3aN8kBw","name":"Wennie-discord-1","subtype":"USER"},"type":"CREATE_IDENTITY"},"ledgerTimestamp":1653354405531,"uuid":"qYvZdxt4TLy9KaYy0rH8Nw","version":"1"}
{"action":{"alias":{"address":"N\u0000sourcecred\u0000discord\u0000MEMBER\u0000user\u0000969197742775758848\u0000","description":"discord/Wennie#5500"},"identityId":"3eMaieRQa5vpMtj3aN8kBw","type":"ADD_ALIAS"},"ledgerTimestamp":1653354405531,"uuid":"IwaOMidTnovdZRiZPB7Mlw","version":"1"}
{"action":{"identity":{"address":"N\u0000sourcecred\u0000core\u0000IDENTITY\u0000pDj4MSdP43UMRXfDVp0hrQ\u0000","aliases":[],"id":"pDj4MSdP43UMRXfDVp0hrQ","name":"fjhods","subtype":"USER"},"type":"CREATE_IDENTITY"},"ledgerTimestamp":1653354405532,"uuid":"9yGkbC9QexfgONRoq9l0qw","version":"1"}
{"action":{"alias":{"address":"N\u0000sourcecred\u0000discord\u0000MEMBER\u0000user\u0000969234211221409872\u0000","description":"discord/fjhods#9237"},"identityId":"pDj4MSdP43UMRXfDVp0hrQ","type":"ADD_ALIAS"},"ledgerTimestamp":1653354405532,"uuid":"6JgOHEKpkNa3Vi8O9nFYfQ","version":"1"}
{"action":{"identity":{"address":"N\u0000sourcecred\u0000core\u0000IDENTITY\u0000Ro7UKfNj7ij5OsKGPKUPdA\u0000","aliases":[],"id":"Ro7UKfNj7ij5OsKGPKUPdA","name":"indigo","subtype":"USER"},"type":"CREATE_IDENTITY"},"ledgerTimestamp":1653354405532,"uuid":"pjqMey7AwUGEMO8LH5oMVQ","version":"1"}
{"action":{"alias":{"address":"N\u0000sourcecred\u0000discord\u0000MEMBER\u0000user\u0000969505506299359232\u0000","description":"discord/indigo#9374"},"identityId":"Ro7UKfNj7ij5OsKGPKUPdA","type":"ADD_ALIAS"},"ledgerTimestamp":1653354405532,"uuid":"Gn9LHqnlPbvtpw1UZOH3aA","version":"1"}
{"action":{"identity":{"address":"N\u0000sourcecred\u0000core\u0000IDENTITY\u0000g6s7gsvwH406aysQlVT3Ow\u0000","aliases":[],"id":"g6s7gsvwH406aysQlVT3Ow","name":"Holmes-Pan","subtype":"USER"},"type":"CREATE_IDENTITY"},"ledgerTimestamp":1653354405532,"uuid":"qVwOZZqfRt3129lA74VRFQ","version":"1"}
{"action":{"alias":{"address":"N\u0000sourcecred\u0000discord\u0000MEMBER\u0000user\u0000969605300845969468\u0000","description":"discord/Holmes-Pan#1645"},"identityId":"g6s7gsvwH406aysQlVT3Ow","type":"ADD_ALIAS"},"ledgerTimestamp":1653354405534,"uuid":"k0cM0F1ZMKwp5y2LoPfWeQ","version":"1"}
{"action":{"identity":{"address":"N\u0000sourcecred\u0000core\u0000IDENTITY\u00003vniWuMrv5Lzjb59E3W8Hw\u0000","aliases":[],"id":"3vniWuMrv5Lzjb59E3W8Hw","name":"JOhn-WAng","subtype":"USER"},"type":"CREATE_IDENTITY"},"ledgerTimestamp":1653354405534,"uuid":"jljeZWiNejWphKiayggvyw","version":"1"}
{"action":{"alias":{"address":"N\u0000sourcecred\u0000discord\u0000MEMBER\u0000user\u0000969850567197331526\u0000","description":"discord/JOhn-WAng#3009"},"identityId":"3vniWuMrv5Lzjb59E3W8Hw","type":"ADD_ALIAS"},"ledgerTimestamp":1653354405534,"uuid":"KTVWlXOFDWGpuLFx92EZXQ","version":"1"}
{"action":{"identity":{"address":"N\u0000sourcecred\u0000core\u0000IDENTITY\u0000zyReFR7JJwA5FpZgn3IXJw\u0000","aliases":[],"id":"zyReFR7JJwA5FpZgn3IXJw","name":"ALLEN","subtype":"USER"},"type":"CREATE_IDENTITY"},"ledgerTimestamp":1653354405534,"uuid":"SO6z471Wj920WGUzGYWDeg","version":"1"}
{"action":{"alias":{"address":"N\u0000sourcecred\u0000discord\u0000MEMBER\u0000user\u0000969870928169295898\u0000","description":"discord/ALLEN#6462"},"identityId":"zyReFR7JJwA5FpZgn3IXJw","type":"ADD_ALIAS"},"ledgerTimestamp":1653354405534,"uuid":"UOYKK5GiRz7je42yAkgO7g","version":"1"}
{"action":{"identity":{"address":"N\u0000sourcecred\u0000core\u0000IDENTITY\u0000llRWqHEGmG0OYe1atNZg4w\u0000","aliases":[],"id":"llRWqHEGmG0OYe1atNZg4w","name":"Wanzi-","subtype":"USER"},"type":"CREATE_IDENTITY"},"ledgerTimestamp":1653354405535,"uuid":"bEvn8rY6a9YJJFA84C2gVw","version":"1"}
{"action":{"alias":{"address":"N\u0000sourcecred\u0000discord\u0000MEMBER\u0000user\u0000969871389299449907\u0000","description":"discord/Wanzi-#4234"},"identityId":"llRWqHEGmG0OYe1atNZg4w","type":"ADD_ALIAS"},"ledgerTimestamp":1653354405535,"uuid":"aaMMF6GB4JPHn9OV5kafZQ","version":"1"}
{"action":{"identity":{"address":"N\u0000sourcecred\u0000core\u0000IDENTITY\u0000EgWUOkB0p5EAmNZ9xM3S2w\u0000","aliases":[],"id":"EgWUOkB0p5EAmNZ9xM3S2w","name":"maruko-eth","subtype":"USER"},"type":"CREATE_IDENTITY"},"ledgerTimestamp":1653354405535,"uuid":"D8LXEMYMZGja5sl3d3gxzA","version":"1"}
{"action":{"alias":{"address":"N\u0000sourcecred\u0000discord\u0000MEMBER\u0000user\u0000969934361535324230\u0000","description":"discord/maruko-eth#7209"},"identityId":"EgWUOkB0p5EAmNZ9xM3S2w","type":"ADD_ALIAS"},"ledgerTimestamp":1653354405535,"uuid":"CMWbtP4s7QyHvmGUVvyb5w","version":"1"}
{"action":{"identity":{"address":"N\u0000sourcecred\u0000core\u0000IDENTITY\u0000hKPdv8HYPmz8RKmahmozjQ\u0000","aliases":[],"id":"hKPdv8HYPmz8RKmahmozjQ","name":"M-left-discord-1","subtype":"USER"},"type":"CREATE_IDENTITY"},"ledgerTimestamp":1653354405535,"uuid":"dAq5Z45Gx9DAk3EfxHKQMg","version":"1"}
{"action":{"alias":{"address":"N\u0000sourcecred\u0000discord\u0000MEMBER\u0000user\u0000969983296282972290\u0000","description":"discord/M-left#7182"},"identityId":"hKPdv8HYPmz8RKmahmozjQ","type":"ADD_ALIAS"},"ledgerTimestamp":1653354405535,"uuid":"Mxi9S4Q8ONNRPYE1Q71zUw","version":"1"}
{"action":{"identity":{"address":"N\u0000sourcecred\u0000core\u0000IDENTITY\u0000EIXVholpombjikbEqnKLcQ\u0000","aliases":[],"id":"EIXVholpombjikbEqnKLcQ","name":"MMMMMusturd","subtype":"USER"},"type":"CREATE_IDENTITY"},"ledgerTimestamp":1653354405535,"uuid":"oolPBLIq5qJLcmdKCp7VjQ","version":"1"}
{"action":{"alias":{"address":"N\u0000sourcecred\u0000discord\u0000MEMBER\u0000user\u0000970243762456522852\u0000","description":"discord/MMMMMusturd#8701"},"identityId":"EIXVholpombjikbEqnKLcQ","type":"ADD_ALIAS"},"ledgerTimestamp":1653354405536,"uuid":"lsdQcriag8blQQbgFDPbRg","version":"1"}
{"action":{"identity":{"address":"N\u0000sourcecred\u0000core\u0000IDENTITY\u0000SDxwGQmfEOXagpXkEqXerA\u0000","aliases":[],"id":"SDxwGQmfEOXagpXkEqXerA","name":"discord-970976075221979147","subtype":"USER"},"type":"CREATE_IDENTITY"},"ledgerTimestamp":1653354405536,"uuid":"HQBcxHRzhg4Yl9qvVOsaiQ","version":"1"}
{"action":{"alias":{"address":"N\u0000sourcecred\u0000discord\u0000MEMBER\u0000user\u0000970976075221979147\u0000","description":"discord/discord-970976075221979147#8361"},"identityId":"SDxwGQmfEOXagpXkEqXerA","type":"ADD_ALIAS"},"ledgerTimestamp":1653354405536,"uuid":"LZu1VGhmruQEMvzixWizfQ","version":"1"}
{"action":{"identity":{"address":"N\u0000sourcecred\u0000core\u0000IDENTITY\u00006I3yCN5Zn9ZdcqDhjhbz2g\u0000","aliases":[],"id":"6I3yCN5Zn9ZdcqDhjhbz2g","name":"WAVE-HAICHAO","subtype":"USER"},"type":"CREATE_IDENTITY"},"ledgerTimestamp":1653354405536,"uuid":"g1tDgZ7j2eKxFrAV0f3j5A","version":"1"}
{"action":{"alias":{"address":"N\u0000sourcecred\u0000discord\u0000MEMBER\u0000user\u0000971044317961519205\u0000","description":"discord/WAVE-HAICHAO#2427"},"identityId":"6I3yCN5Zn9ZdcqDhjhbz2g","type":"ADD_ALIAS"},"ledgerTimestamp":1653354405536,"uuid":"o22bYj4KlmDXNZlNivfVfw","version":"1"}
{"action":{"identity":{"address":"N\u0000sourcecred\u0000core\u0000IDENTITY\u0000lwEWRsZ5ZjGpA3auomwXhQ\u0000","aliases":[],"id":"lwEWRsZ5ZjGpA3auomwXhQ","name":"WAVE-HAICHAO-discord","subtype":"USER"},"type":"CREATE_IDENTITY"},"ledgerTimestamp":1653354405536,"uuid":"1upIaIbl2xGF4CaJ87lvZg","version":"1"}
{"action":{"alias":{"address":"N\u0000sourcecred\u0000discord\u0000MEMBER\u0000user\u0000971046317394632785\u0000","description":"discord/WAVE-HAICHAO#7518"},"identityId":"lwEWRsZ5ZjGpA3auomwXhQ","type":"ADD_ALIAS"},"ledgerTimestamp":1653354405537,"uuid":"s4fOFnq6g3YgUgDvEgsbmg","version":"1"}
{"action":{"identity":{"address":"N\u0000sourcecred\u0000core\u0000IDENTITY\u0000cGKgX3toJMxX3WtxJ59SRA\u0000","aliases":[],"id":"cGKgX3toJMxX3WtxJ59SRA","name":"platinumjohn","subtype":"USER"},"type":"CREATE_IDENTITY"},"ledgerTimestamp":1653354405537,"uuid":"7hwz2Nsgyz7V6RkbRX97fQ","version":"1"}
{"action":{"alias":{"address":"N\u0000sourcecred\u0000discord\u0000MEMBER\u0000user\u0000971244230850781294\u0000","description":"discord/platinumjohn#3103"},"identityId":"cGKgX3toJMxX3WtxJ59SRA","type":"ADD_ALIAS"},"ledgerTimestamp":1653354405537,"uuid":"8TrtXVWH94ZLk01WDLARlA","version":"1"}
{"action":{"identity":{"address":"N\u0000sourcecred\u0000core\u0000IDENTITY\u00000FQnbPgAlyZ9BCmdyHZqng\u0000","aliases":[],"id":"0FQnbPgAlyZ9BCmdyHZqng","name":"Psycho","subtype":"USER"},"type":"CREATE_IDENTITY"},"ledgerTimestamp":1653354405537,"uuid":"OPLZt0bqxYXO8u4fXaKPDw","version":"1"}
{"action":{"alias":{"address":"N\u0000sourcecred\u0000discord\u0000MEMBER\u0000user\u0000971447425250258954\u0000","description":"discord/Psycho#4915"},"identityId":"0FQnbPgAlyZ9BCmdyHZqng","type":"ADD_ALIAS"},"ledgerTimestamp":1653354405537,"uuid":"2mCyiMIYz6WwEi7DUVQhjQ","version":"1"}
{"action":{"identity":{"address":"N\u0000sourcecred\u0000core\u0000IDENTITY\u0000wMkH7U84Ye19xPVEiGVq0w\u0000","aliases":[],"id":"wMkH7U84Ye19xPVEiGVq0w","name":"YIFENGJING","subtype":"USER"},"type":"CREATE_IDENTITY"},"ledgerTimestamp":1653354405537,"uuid":"NdqtqhXnLEQuJaN5JIvbfw","version":"1"}
{"action":{"alias":{"address":"N\u0000sourcecred\u0000discord\u0000MEMBER\u0000user\u0000971706758483562556\u0000","description":"discord/YIFENGJING#8478"},"identityId":"wMkH7U84Ye19xPVEiGVq0w","type":"ADD_ALIAS"},"ledgerTimestamp":1653354405537,"uuid":"FBeKzBjvQZPzNQ93z4NrKQ","version":"1"}
{"action":{"identity":{"address":"N\u0000sourcecred\u0000core\u0000IDENTITY\u0000f2V7JRcqj2ZYyQv9XHbNkQ\u0000","aliases":[],"id":"f2V7JRcqj2ZYyQv9XHbNkQ","name":"monicaweon","subtype":"USER"},"type":"CREATE_IDENTITY"},"ledgerTimestamp":1653354405537,"uuid":"opkWA7uB38E4UGYRwC1Rhw","version":"1"}
{"action":{"alias":{"address":"N\u0000sourcecred\u0000discord\u0000MEMBER\u0000user\u0000971955211306401822\u0000","description":"discord/monicaweon#3194"},"identityId":"f2V7JRcqj2ZYyQv9XHbNkQ","type":"ADD_ALIAS"},"ledgerTimestamp":1653354405538,"uuid":"S2zgQ3h7wNhvLfwLZV5uVg","version":"1"}
{"action":{"identity":{"address":"N\u0000sourcecred\u0000core\u0000IDENTITY\u0000jk2bR09d15ZdxjuqM6svUw\u0000","aliases":[],"id":"jk2bR09d15ZdxjuqM6svUw","name":"Zeno","subtype":"USER"},"type":"CREATE_IDENTITY"},"ledgerTimestamp":1653354405538,"uuid":"nYEx0POD8COmSaBOX1qzaQ","version":"1"}
{"action":{"alias":{"address":"N\u0000sourcecred\u0000discord\u0000MEMBER\u0000user\u0000972000753449320498\u0000","description":"discord/Zeno#8932"},"identityId":"jk2bR09d15ZdxjuqM6svUw","type":"ADD_ALIAS"},"ledgerTimestamp":1653354405538,"uuid":"l3XIzMRL8h7pk1kD6ygdFA","version":"1"}
{"action":{"identity":{"address":"N\u0000sourcecred\u0000core\u0000IDENTITY\u0000V0cy9jQ3YlVpb2lx0TA8ig\u0000","aliases":[],"id":"V0cy9jQ3YlVpb2lx0TA8ig","name":"discord-972057668837605397","subtype":"USER"},"type":"CREATE_IDENTITY"},"ledgerTimestamp":1653354405538,"uuid":"2mxbXTztDpnk1O7rwb9VVA","version":"1"}
{"action":{"alias":{"address":"N\u0000sourcecred\u0000discord\u0000MEMBER\u0000user\u0000972057668837605397\u0000","description":"discord/discord-972057668837605397#1207"},"identityId":"V0cy9jQ3YlVpb2lx0TA8ig","type":"ADD_ALIAS"},"ledgerTimestamp":1653354405538,"uuid":"D9YuALNrFbI8g25ijg3cgw","version":"1"}
{"action":{"identity":{"address":"N\u0000sourcecred\u0000core\u0000IDENTITY\u0000C9hrbjfwvxltvVr1hLtW6w\u0000","aliases":[],"id":"C9hrbjfwvxltvVr1hLtW6w","name":"Doris-q","subtype":"USER"},"type":"CREATE_IDENTITY"},"ledgerTimestamp":1653354405538,"uuid":"mXZ3eemlzKYYEdkMQwKhvQ","version":"1"}
{"action":{"alias":{"address":"N\u0000sourcecred\u0000discord\u0000MEMBER\u0000user\u0000972092953864585226\u0000","description":"discord/Doris-q#3497"},"identityId":"C9hrbjfwvxltvVr1hLtW6w","type":"ADD_ALIAS"},"ledgerTimestamp":1653354405538,"uuid":"anLAI1zgQBztviq96bV3Ew","version":"1"}
{"action":{"identity":{"address":"N\u0000sourcecred\u0000core\u0000IDENTITY\u0000YZGa9luOa1XJ6ydxYzEamA\u0000","aliases":[],"id":"YZGa9luOa1XJ6ydxYzEamA","name":"rere-fire","subtype":"USER"},"type":"CREATE_IDENTITY"},"ledgerTimestamp":1653354405538,"uuid":"M8Cwf9ELHz1rAGApcdWMUA","version":"1"}
{"action":{"alias":{"address":"N\u0000sourcecred\u0000discord\u0000MEMBER\u0000user\u0000972097816044400710\u0000","description":"discord/rere-fire#6582"},"identityId":"YZGa9luOa1XJ6ydxYzEamA","type":"ADD_ALIAS"},"ledgerTimestamp":1653354405538,"uuid":"RnnmUjeU2C0xrbpqleaiWQ","version":"1"}
{"action":{"identity":{"address":"N\u0000sourcecred\u0000core\u0000IDENTITY\u0000kLBWXIRRterKM0o3cNx08Q\u0000","aliases":[],"id":"kLBWXIRRterKM0o3cNx08Q","name":"lq","subtype":"USER"},"type":"CREATE_IDENTITY"},"ledgerTimestamp":1653354405538,"uuid":"BWAXepxj3VoaGunaiDbSyw","version":"1"}
{"action":{"alias":{"address":"N\u0000sourcecred\u0000discord\u0000MEMBER\u0000user\u0000972108344112320572\u0000","description":"discord/lq#7005"},"identityId":"kLBWXIRRterKM0o3cNx08Q","type":"ADD_ALIAS"},"ledgerTimestamp":1653354405539,"uuid":"mPjSXeV2v3B9iLo35g3S4g","version":"1"}
{"action":{"identity":{"address":"N\u0000sourcecred\u0000core\u0000IDENTITY\u0000ZfQ5ulQLrJawRIyqQ4HZ1Q\u0000","aliases":[],"id":"ZfQ5ulQLrJawRIyqQ4HZ1Q","name":"Daniel-Yan","subtype":"USER"},"type":"CREATE_IDENTITY"},"ledgerTimestamp":1653354405539,"uuid":"RNZRUJb1YsMoDiPQ4Xj7qQ","version":"1"}
{"action":{"alias":{"address":"N\u0000sourcecred\u0000discord\u0000MEMBER\u0000user\u0000972111297577623622\u0000","description":"discord/Daniel-Yan#8627"},"identityId":"ZfQ5ulQLrJawRIyqQ4HZ1Q","type":"ADD_ALIAS"},"ledgerTimestamp":1653354405539,"uuid":"rRjdgPyMTMoL2YV9SwgFMA","version":"1"}
{"action":{"identity":{"address":"N\u0000sourcecred\u0000core\u0000IDENTITY\u0000I1mqWYfJHJmE5p6cGjgOOQ\u0000","aliases":[],"id":"I1mqWYfJHJmE5p6cGjgOOQ","name":"JY","subtype":"USER"},"type":"CREATE_IDENTITY"},"ledgerTimestamp":1653354405539,"uuid":"3d3Z9upZ08w7V6iWeblmew","version":"1"}
{"action":{"alias":{"address":"N\u0000sourcecred\u0000discord\u0000MEMBER\u0000user\u0000972115329151041556\u0000","description":"discord/JY#7220"},"identityId":"I1mqWYfJHJmE5p6cGjgOOQ","type":"ADD_ALIAS"},"ledgerTimestamp":1653354405539,"uuid":"DxEpKVaRbkWOEGk6rDdqtQ","version":"1"}
{"action":{"identity":{"address":"N\u0000sourcecred\u0000core\u0000IDENTITY\u0000oRGTnVzneYMOe89U5uvYlw\u0000","aliases":[],"id":"oRGTnVzneYMOe89U5uvYlw","name":"chucksonwheel","subtype":"USER"},"type":"CREATE_IDENTITY"},"ledgerTimestamp":1653354405540,"uuid":"bd0uy5azQ7rkh8p6PnK60w","version":"1"}
{"action":{"alias":{"address":"N\u0000sourcecred\u0000discord\u0000MEMBER\u0000user\u0000972436337074524160\u0000","description":"discord/chucksonwheel#3873"},"identityId":"oRGTnVzneYMOe89U5uvYlw","type":"ADD_ALIAS"},"ledgerTimestamp":1653354405541,"uuid":"JX1TrtxYlPiZ3klz6SRDkA","version":"1"}
{"action":{"identity":{"address":"N\u0000sourcecred\u0000core\u0000IDENTITY\u0000iXkf96z7C6gaixBqfYHwAA\u0000","aliases":[],"id":"iXkf96z7C6gaixBqfYHwAA","name":"CyberHuang","subtype":"USER"},"type":"CREATE_IDENTITY"},"ledgerTimestamp":1653354405541,"uuid":"UD1BbC6R3eIA56TK8mnPbg","version":"1"}
{"action":{"alias":{"address":"N\u0000sourcecred\u0000discord\u0000MEMBER\u0000user\u0000972668606133448714\u0000","description":"discord/CyberHuang#9324"},"identityId":"iXkf96z7C6gaixBqfYHwAA","type":"ADD_ALIAS"},"ledgerTimestamp":1653354405541,"uuid":"LnyabnaGFxwRqyAS4BTPRA","version":"1"}
{"action":{"identity":{"address":"N\u0000sourcecred\u0000core\u0000IDENTITY\u0000mfRxbaCVU1NNS8wxKmfZvw\u0000","aliases":[],"id":"mfRxbaCVU1NNS8wxKmfZvw","name":"tongruwei","subtype":"USER"},"type":"CREATE_IDENTITY"},"ledgerTimestamp":1653354405541,"uuid":"3W5NdPJdmGyQKKcWPjqG9A","version":"1"}
{"action":{"alias":{"address":"N\u0000sourcecred\u0000discord\u0000MEMBER\u0000user\u0000972706023871774753\u0000","description":"discord/tongruwei#8558"},"identityId":"mfRxbaCVU1NNS8wxKmfZvw","type":"ADD_ALIAS"},"ledgerTimestamp":1653354405541,"uuid":"TEK8PgDW8tBBlx9sOXudqg","version":"1"}
{"action":{"identity":{"address":"N\u0000sourcecred\u0000core\u0000IDENTITY\u0000d5ANkzLezeXF1RIbbfkxSg\u0000","aliases":[],"id":"d5ANkzLezeXF1RIbbfkxSg","name":"GGman","subtype":"USER"},"type":"CREATE_IDENTITY"},"ledgerTimestamp":1653354405541,"uuid":"eu9bhYXC4k88REOPAvqUaw","version":"1"}
{"action":{"alias":{"address":"N\u0000sourcecred\u0000discord\u0000MEMBER\u0000user\u0000973065859239116810\u0000","description":"discord/GGman#3922"},"identityId":"d5ANkzLezeXF1RIbbfkxSg","type":"ADD_ALIAS"},"ledgerTimestamp":1653354405541,"uuid":"LVxSBZv76NG6D9EJlXfxSQ","version":"1"}
{"action":{"identity":{"address":"N\u0000sourcecred\u0000core\u0000IDENTITY\u0000bTRE2FpgBjQDnNuG8UQdmA\u0000","aliases":[],"id":"bTRE2FpgBjQDnNuG8UQdmA","name":"antiuo","subtype":"USER"},"type":"CREATE_IDENTITY"},"ledgerTimestamp":1653354405542,"uuid":"OaU4wpz89AvIqu3ONPRBOA","version":"1"}
{"action":{"alias":{"address":"N\u0000sourcecred\u0000discord\u0000MEMBER\u0000user\u0000973478406610104330\u0000","description":"discord/antiuo#5201"},"identityId":"bTRE2FpgBjQDnNuG8UQdmA","type":"ADD_ALIAS"},"ledgerTimestamp":1653354405542,"uuid":"81RI2C9pOJ1Duw7B4Ij6jg","version":"1"}
{"action":{"identity":{"address":"N\u0000sourcecred\u0000core\u0000IDENTITY\u0000SlTAAde8UAAvkzAUB5UkVw\u0000","aliases":[],"id":"SlTAAde8UAAvkzAUB5UkVw","name":"CaptainLeon","subtype":"USER"},"type":"CREATE_IDENTITY"},"ledgerTimestamp":1653354405542,"uuid":"QXRWNgfPGRltROpmek7omw","version":"1"}
{"action":{"alias":{"address":"N\u0000sourcecred\u0000discord\u0000MEMBER\u0000user\u0000973493490635931650\u0000","description":"discord/CaptainLeon#2832"},"identityId":"SlTAAde8UAAvkzAUB5UkVw","type":"ADD_ALIAS"},"ledgerTimestamp":1653354405542,"uuid":"XBV5NKVoGO9XVDV2oS91JA","version":"1"}
{"action":{"identity":{"address":"N\u0000sourcecred\u0000core\u0000IDENTITY\u0000sZBfagsEVC3vh5RNvk64eA\u0000","aliases":[],"id":"sZBfagsEVC3vh5RNvk64eA","name":"Mortise-Labs","subtype":"USER"},"type":"CREATE_IDENTITY"},"ledgerTimestamp":1653354405542,"uuid":"5KaLVPyS6d2CQFxNUl5URw","version":"1"}
{"action":{"alias":{"address":"N\u0000sourcecred\u0000discord\u0000MEMBER\u0000user\u0000973515487185088532\u0000","description":"discord/Mortise-Labs#9198"},"identityId":"sZBfagsEVC3vh5RNvk64eA","type":"ADD_ALIAS"},"ledgerTimestamp":1653354405542,"uuid":"BWhop6dRDxPMlK8BernLEw","version":"1"}
{"action":{"identity":{"address":"N\u0000sourcecred\u0000core\u0000IDENTITY\u0000OdADij9hJWZnpyMALzoDHA\u0000","aliases":[],"id":"OdADij9hJWZnpyMALzoDHA","name":"--YuJ","subtype":"USER"},"type":"CREATE_IDENTITY"},"ledgerTimestamp":1653354405542,"uuid":"SMdn75gNQbDoLZ3JrgUZGQ","version":"1"}
{"action":{"alias":{"address":"N\u0000sourcecred\u0000discord\u0000MEMBER\u0000user\u0000973548831302103061\u0000","description":"discord/--YuJ#1390"},"identityId":"OdADij9hJWZnpyMALzoDHA","type":"ADD_ALIAS"},"ledgerTimestamp":1653354405543,"uuid":"Wenq1ppWE52QKEZXU01oXg","version":"1"}
{"action":{"identity":{"address":"N\u0000sourcecred\u0000core\u0000IDENTITY\u0000BmkS9XaemaS8TjGWqfGyoQ\u0000","aliases":[],"id":"BmkS9XaemaS8TjGWqfGyoQ","name":"YunLi","subtype":"USER"},"type":"CREATE_IDENTITY"},"ledgerTimestamp":1653354405543,"uuid":"ny8XBOncKxQKNtRvZE0arA","version":"1"}
{"action":{"alias":{"address":"N\u0000sourcecred\u0000discord\u0000MEMBER\u0000user\u0000973779984873291816\u0000","description":"discord/YunLi#2630"},"identityId":"BmkS9XaemaS8TjGWqfGyoQ","type":"ADD_ALIAS"},"ledgerTimestamp":1653354405543,"uuid":"FYoKZPFJylMGFPvU9orNoQ","version":"1"}
{"action":{"identity":{"address":"N\u0000sourcecred\u0000core\u0000IDENTITY\u00001zCE2yJdE9w4kpfaWyFx1Q\u0000","aliases":[],"id":"1zCE2yJdE9w4kpfaWyFx1Q","name":"feijun","subtype":"USER"},"type":"CREATE_IDENTITY"},"ledgerTimestamp":1653354405543,"uuid":"nDRpI0loo4a2Vs5BQKQgew","version":"1"}
{"action":{"alias":{"address":"N\u0000sourcecred\u0000discord\u0000MEMBER\u0000user\u0000974275371086282752\u0000","description":"discord/feijun#3964"},"identityId":"1zCE2yJdE9w4kpfaWyFx1Q","type":"ADD_ALIAS"},"ledgerTimestamp":1653354405543,"uuid":"TL5LjeRb1N6aGKP1JVVbQw","version":"1"}
{"action":{"identity":{"address":"N\u0000sourcecred\u0000core\u0000IDENTITY\u00005PLLEAmEJr71eQsefpf05w\u0000","aliases":[],"id":"5PLLEAmEJr71eQsefpf05w","name":"Mrstraw","subtype":"USER"},"type":"CREATE_IDENTITY"},"ledgerTimestamp":1653354405543,"uuid":"41gaaC0GRxPGU7nrbLuYJw","version":"1"}
{"action":{"alias":{"address":"N\u0000sourcecred\u0000discord\u0000MEMBER\u0000user\u0000978143499293691925\u0000","description":"discord/Mrstraw#7491"},"identityId":"5PLLEAmEJr71eQsefpf05w","type":"ADD_ALIAS"},"ledgerTimestamp":1653354405543,"uuid":"S3wWbP45m91tzxIjv3iLnQ","version":"1"}
{"action":{"identity":{"address":"N\u0000sourcecred\u0000core\u0000IDENTITY\u0000UV3p8LkxvNiRvmh1gllHRA\u0000","aliases":[],"id":"UV3p8LkxvNiRvmh1gllHRA","name":"decentralion","subtype":"USER"},"type":"CREATE_IDENTITY"},"ledgerTimestamp":1653354405817,"uuid":"4pkaMjUEgafVXVzrSO1ADQ","version":"1"}
{"action":{"alias":{"address":"N\u0000sourcecred\u0000github\u0000USERLIKE\u0000USER\u0000decentralion\u0000","description":"github/[@decentralion](https://github.com/decentralion)"},"identityId":"UV3p8LkxvNiRvmh1gllHRA","type":"ADD_ALIAS"},"ledgerTimestamp":1653354405817,"uuid":"OjcWz0CdvKjkp72rGlvswA","version":"1"}
{"action":{"identity":{"address":"N\u0000sourcecred\u0000core\u0000IDENTITY\u00007ngONWpay4QDLVP1ENLTDA\u0000","aliases":[],"id":"7ngONWpay4QDLVP1ENLTDA","name":"credbot","subtype":"BOT"},"type":"CREATE_IDENTITY"},"ledgerTimestamp":1653354405817,"uuid":"XamfddBND6U7AspI9jJxgg","version":"1"}
{"action":{"alias":{"address":"N\u0000sourcecred\u0000github\u0000USERLIKE\u0000BOT\u0000credbot\u0000","description":"github/[@credbot](https://github.com/credbot)"},"identityId":"7ngONWpay4QDLVP1ENLTDA","type":"ADD_ALIAS"},"ledgerTimestamp":1653354405818,"uuid":"tleH35h9qKLWOeyQUKM6SQ","version":"1"}
{"action":{"identity":{"address":"N\u0000sourcecred\u0000core\u0000IDENTITY\u0000S0xHEC0UN3ygDanRRemZYQ\u0000","aliases":[],"id":"S0xHEC0UN3ygDanRRemZYQ","name":"wchargin","subtype":"USER"},"type":"CREATE_IDENTITY"},"ledgerTimestamp":1653354405818,"uuid":"4yrRMfgBbJrsNEBdimnG4A","version":"1"}
{"action":{"alias":{"address":"N\u0000sourcecred\u0000github\u0000USERLIKE\u0000USER\u0000wchargin\u0000","description":"github/[@wchargin](https://github.com/wchargin)"},"identityId":"S0xHEC0UN3ygDanRRemZYQ","type":"ADD_ALIAS"},"ledgerTimestamp":1653354405818,"uuid":"G3j0YGXaCgltewyYhBsK8Q","version":"1"}
{"action":{"identity":{"address":"N\u0000sourcecred\u0000core\u0000IDENTITY\u00006Yv0XoRB933Entr0aWXg4A\u0000","aliases":[],"id":"6Yv0XoRB933Entr0aWXg4A","name":"SourceCred","subtype":"PROJECT"},"type":"CREATE_IDENTITY"},"ledgerTimestamp":1653354405997,"uuid":"Zm2fA2kXV8hzBl7P4Yt0xQ","version":"1"}
{"action":{"identityId":"6Yv0XoRB933Entr0aWXg4A","type":"TOGGLE_ACTIVATION"},"ledgerTimestamp":1653354405997,"uuid":"CywT1YwZ14mdzy6eNsOSdQ","version":"1"}
