{"action":{"identity":{"address":"N\u0000sourcecred\u0000core\u0000IDENTITY\u0000hVuAnHMWeixcXsrTECyOBg\u0000","aliases":[],"id":"hVuAnHMWeixcXsrTECyOBg","name":"Owen-G--G-","subtype":"USER"},"type":"CREATE_IDENTITY"},"ledgerTimestamp":1643768149541,"uuid":"aHmPCzQymuKvX2I1whz9hA","version":"1"}
{"action":{"alias":{"address":"N\u0000sourcecred\u0000discord\u0000MEMBER\u0000user\u0000307827662196310016\u0000","description":"discord/Owen-G--G-#0187"},"identityId":"hVuAnHMWeixcXsrTECyOBg","type":"ADD_ALIAS"},"ledgerTimestamp":1643768149541,"uuid":"EU2iynGUWnzbe58qbWVmZg","version":"1"}
{"action":{"identity":{"address":"N\u0000sourcecred\u0000core\u0000IDENTITY\u0000GVslATQOGEAAh4NVBreNLA\u0000","aliases":[],"id":"GVslATQOGEAAh4NVBreNLA","name":"Michelle42","subtype":"USER"},"type":"CREATE_IDENTITY"},"ledgerTimestamp":1643768149542,"uuid":"rqQ8FobDAxDjpMExxylqQw","version":"1"}
{"action":{"alias":{"address":"N\u0000sourcecred\u0000discord\u0000MEMBER\u0000user\u0000932906546982178817\u0000","description":"discord/Michelle42#9528"},"identityId":"GVslATQOGEAAh4NVBreNLA","type":"ADD_ALIAS"},"ledgerTimestamp":1643768149544,"uuid":"yYQDSLXFgrzjzXQlPKuV2g","version":"1"}
{"action":{"identity":{"address":"N\u0000sourcecred\u0000core\u0000IDENTITY\u0000swRGx6NgE096ZoJdxbXQxw\u0000","aliases":[],"id":"swRGx6NgE096ZoJdxbXQxw","name":"mua-miles","subtype":"USER"},"type":"CREATE_IDENTITY"},"ledgerTimestamp":1643768149544,"uuid":"Q6e02LvplPxvYNwObGOokw","version":"1"}
{"action":{"alias":{"address":"N\u0000sourcecred\u0000discord\u0000MEMBER\u0000user\u0000932919660192620555\u0000","description":"discord/mua-miles#0937"},"identityId":"swRGx6NgE096ZoJdxbXQxw","type":"ADD_ALIAS"},"ledgerTimestamp":1643768149544,"uuid":"90Xtdc0tB42mLa5zgekQTQ","version":"1"}
{"action":{"identity":{"address":"N\u0000sourcecred\u0000core\u0000IDENTITY\u0000jjYmYpGCwzQoaxHdIn8pyg\u0000","aliases":[],"id":"jjYmYpGCwzQoaxHdIn8pyg","name":"mua-sourcecred","subtype":"BOT"},"type":"CREATE_IDENTITY"},"ledgerTimestamp":1643768149545,"uuid":"G9G4hgkdvCJ5fDGOoppNmw","version":"1"}
{"action":{"alias":{"address":"N\u0000sourcecred\u0000discord\u0000MEMBER\u0000bot\u0000933581993118167130\u0000","description":"discord/mua-sourcecred#7651"},"identityId":"jjYmYpGCwzQoaxHdIn8pyg","type":"ADD_ALIAS"},"ledgerTimestamp":1643768149545,"uuid":"Xk5jhGP0DfzDyRXcEqJvIg","version":"1"}
{"action":{"identity":{"address":"N\u0000sourcecred\u0000core\u0000IDENTITY\u00003GVLteDzfpbr9q8Vxbxwqw\u0000","aliases":[],"id":"3GVLteDzfpbr9q8Vxbxwqw","name":"decentralion","subtype":"USER"},"type":"CREATE_IDENTITY"},"ledgerTimestamp":1643768149896,"uuid":"9LGO92JznvfW3AmPlr4xhg","version":"1"}
{"action":{"alias":{"address":"N\u0000sourcecred\u0000github\u0000USERLIKE\u0000USER\u0000decentralion\u0000","description":"github/[@decentralion](https://github.com/decentralion)"},"identityId":"3GVLteDzfpbr9q8Vxbxwqw","type":"ADD_ALIAS"},"ledgerTimestamp":1643768149897,"uuid":"ju2XagKPy4VzRbURjGjD6w","version":"1"}
{"action":{"identity":{"address":"N\u0000sourcecred\u0000core\u0000IDENTITY\u0000IRnurypyyv7CPBFy2ECm6g\u0000","aliases":[],"id":"IRnurypyyv7CPBFy2ECm6g","name":"credbot","subtype":"BOT"},"type":"CREATE_IDENTITY"},"ledgerTimestamp":1643768149897,"uuid":"NFEu1Xdeb0m8MSpaJP8hpg","version":"1"}
{"action":{"alias":{"address":"N\u0000sourcecred\u0000github\u0000USERLIKE\u0000BOT\u0000credbot\u0000","description":"github/[@credbot](https://github.com/credbot)"},"identityId":"IRnurypyyv7CPBFy2ECm6g","type":"ADD_ALIAS"},"ledgerTimestamp":1643768149897,"uuid":"y9hoE6jV6wXpkCPaYrYjEg","version":"1"}
{"action":{"identity":{"address":"N\u0000sourcecred\u0000core\u0000IDENTITY\u00002bxW5JjrbL2aEgzZUbJIZg\u0000","aliases":[],"id":"2bxW5JjrbL2aEgzZUbJIZg","name":"wchargin","subtype":"USER"},"type":"CREATE_IDENTITY"},"ledgerTimestamp":1643768149897,"uuid":"Gvk3Tmmea7c971kzpDxbNw","version":"1"}
{"action":{"alias":{"address":"N\u0000sourcecred\u0000github\u0000USERLIKE\u0000USER\u0000wchargin\u0000","description":"github/[@wchargin](https://github.com/wchargin)"},"identityId":"2bxW5JjrbL2aEgzZUbJIZg","type":"ADD_ALIAS"},"ledgerTimestamp":1643768149897,"uuid":"WLDiwAhlQh8GrQXvFnnt2A","version":"1"}
{"action":{"identity":{"address":"N\u0000sourcecred\u0000core\u0000IDENTITY\u0000UDEMx5nwLQ3dPj2tJZeBiA\u0000","aliases":[],"id":"UDEMx5nwLQ3dPj2tJZeBiA","name":"SourceCred","subtype":"PROJECT"},"type":"CREATE_IDENTITY"},"ledgerTimestamp":1643768149975,"uuid":"P9qxkI5ZAxYIeacqKVB2dA","version":"1"}
{"action":{"identityId":"UDEMx5nwLQ3dPj2tJZeBiA","type":"TOGGLE_ACTIVATION"},"ledgerTimestamp":1643768149975,"uuid":"mFy1kJhkMDQHLSydSxj4lw","version":"1"}
